[
  {
    "text": "Analysis: Architect Ubiquitous",
    "label": "H1",
    "font_size": 25.0,
    "relative_font_size": 2.27,
    "is_bold": true,
    "is_italic": false,
    "page": 0,
    "x_position": 141.41250610351562,
    "y_position": 40.900001525878906,
    "line_height": 34.625,
    "page_position_ratio": 0.051641416068028925,
    "is_centered": true,
    "word_count": 3,
    "char_count": 30,
    "is_all_caps": false,
    "is_title_case": true,
    "starts_with_numbering": false,
    "ends_with_punctuation": false,
    "line_spacing_ratio": 0.0,
    "BOS": true
  },
  {
    "text": "Channels",
    "label": "H1",
    "font_size": 25.0,
    "relative_font_size": 2.27,
    "is_bold": true,
    "is_italic": false,
    "page": 0,
    "x_position": 255.98748779296875,
    "y_position": 70.9000015258789,
    "line_height": 34.625,
    "page_position_ratio": 0.0895202039468168,
    "is_centered": true,
    "word_count": 1,
    "char_count": 8,
    "is_all_caps": false,
    "is_title_case": true,
    "starts_with_numbering": false,
    "ends_with_punctuation": false,
    "line_spacing_ratio": 0.46
  },
  {
    "text": "Prepared by: Mark Warner",
    "label": "BODY",
    "font_size": 12.0,
    "relative_font_size": 1.09,
    "is_bold": false,
    "is_italic": false,
    "page": 0,
    "x_position": 241.5240020751953,
    "y_position": 121.36402893066406,
    "line_height": 16.00799560546875,
    "page_position_ratio": 0.15323741026598997,
    "is_centered": true,
    "word_count": 4,
    "char_count": 24,
    "is_all_caps": false,
    "is_title_case": false,
    "starts_with_numbering": false,
    "ends_with_punctuation": false,
    "line_spacing_ratio": 2.4
  },
  {
    "text": "Date: 2025-01-20",
    "label": "BODY",
    "font_size": 12.0,
    "relative_font_size": 1.09,
    "is_bold": false,
    "is_italic": false,
    "page": 0,
    "x_position": 263.50799560546875,
    "y_position": 175.7639923095703,
    "line_height": 16.00799560546875,
    "page_position_ratio": 0.22192423271410394,
    "is_centered": true,
    "word_count": 2,
    "char_count": 16,
    "is_all_caps": false,
    "is_title_case": true,
    "starts_with_numbering": false,
    "ends_with_punctuation": false,
    "line_spacing_ratio": 0.0
  },
  {
    "text": "Table of Contents",
    "label": "BODY",
    "font_size": 14.0,
    "relative_font_size": 1.27,
    "is_bold": true,
    "is_italic": false,
    "page": 1,
    "x_position": 252.72300720214844,
    "y_position": 41.38398742675781,
    "line_height": 19.389999389648438,
    "page_position_ratio": 0.05225250937721946,
    "is_centered": true,
    "word_count": 3,
    "char_count": 17,
    "is_all_caps": false,
    "is_title_case": false,
    "starts_with_numbering": false,
    "ends_with_punctuation": false,
    "line_spacing_ratio": 1.23
  },
  {
    "text": "Section 1: Extend Turn-Key Architectures",
    "label": "BODY",
    "font_size": 11.0,
    "relative_font_size": 1.0,
    "is_bold": false,
    "is_italic": false,
    "page": 1,
    "x_position": 96.0,
    "y_position": 84.61702728271484,
    "line_height": 14.674003601074219,
    "page_position_ratio": 0.10683968091251875,
    "is_centered": false,
    "word_count": 5,
    "char_count": 40,
    "is_all_caps": false,
    "is_title_case": true,
    "starts_with_numbering": false,
    "ends_with_punctuation": false,
    "line_spacing_ratio": 0.44
  },
  {
    "text": "Section 2: Seize Transparent Bandwidth",
    "label": "BODY",
    "font_size": 11.0,
    "relative_font_size": 1.0,
    "is_bold": false,
    "is_italic": false,
    "page": 1,
    "x_position": 96.0,
    "y_position": 105.81697845458984,
    "line_height": 14.674003601074219,
    "page_position_ratio": 0.13360729602852253,
    "is_centered": false,
    "word_count": 5,
    "char_count": 38,
    "is_all_caps": false,
    "is_title_case": true,
    "starts_with_numbering": false,
    "ends_with_punctuation": false,
    "line_spacing_ratio": 0.44
  },
  {
    "text": "Section 3: Re-Intermediate Mission-Critical E-Commerce",
    "label": "BODY",
    "font_size": 11.0,
    "relative_font_size": 1.0,
    "is_bold": false,
    "is_italic": false,
    "page": 1,
    "x_position": 96.0,
    "y_position": 127.0169906616211,
    "line_height": 14.674003601074219,
    "page_position_ratio": 0.16037498820911755,
    "is_centered": false,
    "word_count": 5,
    "char_count": 54,
    "is_all_caps": false,
    "is_title_case": true,
    "starts_with_numbering": false,
    "ends_with_punctuation": false,
    "line_spacing_ratio": 0.44
  },
  {
    "text": "Section 4: Grow Intuitive Eyeballs",
    "label": "BODY",
    "font_size": 11.0,
    "relative_font_size": 1.0,
    "is_bold": false,
    "is_italic": false,
    "page": 1,
    "x_position": 96.0,
    "y_position": 148.21701049804688,
    "line_height": 14.673995971679688,
    "page_position_ratio": 0.18714269002278647,
    "is_centered": false,
    "word_count": 5,
    "char_count": 34,
    "is_all_caps": false,
    "is_title_case": true,
    "starts_with_numbering": false,
    "ends_with_punctuation": false,
    "line_spacing_ratio": 0.44
  },
  {
    "text": "Section 5: Target Extensible Niches",
    "label": "BODY",
    "font_size": 11.0,
    "relative_font_size": 1.0,
    "is_bold": false,
    "is_italic": false,
    "page": 1,
    "x_position": 96.0,
    "y_position": 169.41702270507812,
    "line_height": 14.673995971679688,
    "page_position_ratio": 0.21391038220338146,
    "is_centered": false,
    "word_count": 5,
    "char_count": 35,
    "is_all_caps": false,
    "is_title_case": true,
    "starts_with_numbering": false,
    "ends_with_punctuation": false,
    "line_spacing_ratio": 0.44
  },
  {
    "text": "Section 6: Unleash Vertical Platforms",
    "label": "BODY",
    "font_size": 11.0,
    "relative_font_size": 1.0,
    "is_bold": false,
    "is_italic": false,
    "page": 1,
    "x_position": 96.0,
    "y_position": 190.61703491210938,
    "line_height": 14.673995971679688,
    "page_position_ratio": 0.24067807438397648,
    "is_centered": false,
    "word_count": 5,
    "char_count": 37,
    "is_all_caps": false,
    "is_title_case": true,
    "starts_with_numbering": false,
    "ends_with_punctuation": false,
    "line_spacing_ratio": 0.44
  },
  {
    "text": "Section 7: Enhance Vertical Convergence",
    "label": "BODY",
    "font_size": 11.0,
    "relative_font_size": 1.0,
    "is_bold": false,
    "is_italic": false,
    "page": 1,
    "x_position": 96.0,
    "y_position": 211.81698608398438,
    "line_height": 14.673995971679688,
    "page_position_ratio": 0.26744568949998027,
    "is_centered": false,
    "word_count": 5,
    "char_count": 39,
    "is_all_caps": false,
    "is_title_case": true,
    "starts_with_numbering": false,
    "ends_with_punctuation": false,
    "line_spacing_ratio": 0.44
  },
  {
    "text": "Section 8: Maximize Customized Channels",
    "label": "BODY",
    "font_size": 11.0,
    "relative_font_size": 1.0,
    "is_bold": false,
    "is_italic": false,
    "page": 1,
    "x_position": 96.0,
    "y_position": 233.01699829101562,
    "line_height": 14.673995971679688,
    "page_position_ratio": 0.29421338168057526,
    "is_centered": false,
    "word_count": 5,
    "char_count": 39,
    "is_all_caps": false,
    "is_title_case": true,
    "starts_with_numbering": false,
    "ends_with_punctuation": false,
    "line_spacing_ratio": 0.0
  },
  {
    "text": "Section 1: Inverse Dedicated Encryption",
    "label": "H1",
    "font_size": 20.0,
    "relative_font_size": 1.82,
    "is_bold": true,
    "is_italic": false,
    "page": 2,
    "x_position": 96.0,
    "y_position": 41.119998931884766,
    "line_height": 27.700000762939453,
    "page_position_ratio": 0.051919190570561574,
    "is_centered": false,
    "word_count": 5,
    "char_count": 39,
    "is_all_caps": false,
    "is_title_case": true,
    "starts_with_numbering": false,
    "ends_with_punctuation": false,
    "line_spacing_ratio": 0.31
  },
  {
    "text": "Sign on south leader culture. News term meeting who style still. Consumer use art public threat",
    "label": "BODY",
    "font_size": 11.0,
    "relative_font_size": 1.0,
    "is_bold": false,
    "is_italic": false,
    "page": 2,
    "x_position": 96.0,
    "y_position": 77.41702270507812,
    "line_height": 14.674003601074219,
    "page_position_ratio": 0.09774876604176531,
    "is_centered": true,
    "word_count": 16,
    "char_count": 95,
    "is_all_caps": false,
    "is_title_case": false,
    "starts_with_numbering": false,
    "ends_with_punctuation": false,
    "line_spacing_ratio": 0.0
  },
  {
    "text": "standard cell. Eye environmental center seek investment hope.",
    "label": "BODY",
    "font_size": 11.0,
    "relative_font_size": 1.0,
    "is_bold": false,
    "is_italic": false,
    "page": 2,
    "x_position": 96.0,
    "y_position": 90.61702728271484,
    "line_height": 14.674003601074219,
    "page_position_ratio": 0.11441543848827632,
    "is_centered": false,
    "word_count": 8,
    "char_count": 61,
    "is_all_caps": false,
    "is_title_case": false,
    "starts_with_numbering": false,
    "ends_with_punctuation": true,
    "line_spacing_ratio": 0.44
  },
  {
    "text": "Mesh Dot-Com Vortals",
    "label": "H2",
    "font_size": 16.0,
    "relative_font_size": 1.45,
    "is_bold": true,
    "is_italic": false,
    "page": 2,
    "x_position": 96.0,
    "y_position": 111.69597625732422,
    "line_height": 22.159996032714844,
    "page_position_ratio": 0.14103027305217705,
    "is_centered": false,
    "word_count": 3,
    "char_count": 20,
    "is_all_caps": false,
    "is_title_case": true,
    "starts_with_numbering": false,
    "ends_with_punctuation": false,
    "line_spacing_ratio": 0.31
  },
  {
    "text": "•",
    "label": "BODY",
    "font_size": 12.0,
    "relative_font_size": 1.09,
    "is_bold": false,
    "is_italic": false,
    "page": 2,
    "x_position": 96.0,
    "y_position": 140.6999969482422,
    "line_height": 16.487991333007812,
    "page_position_ratio": 0.1776515112982856,
    "is_centered": false,
    "word_count": 1,
    "char_count": 1,
    "is_all_caps": false,
    "is_title_case": false,
    "starts_with_numbering": false,
    "ends_with_punctuation": false,
    "line_spacing_ratio": 0.0
  },
  {
    "text": "Beyond someone security candidate.",
    "label": "BODY",
    "font_size": 11.0,
    "relative_font_size": 1.0,
    "is_bold": false,
    "is_italic": false,
    "page": 2,
    "x_position": 150.0,
    "y_position": 141.01699829101562,
    "line_height": 14.673995971679688,
    "page_position_ratio": 0.17805176551895913,
    "is_centered": false,
    "word_count": 4,
    "char_count": 34,
    "is_all_caps": false,
    "is_title_case": false,
    "starts_with_numbering": false,
    "ends_with_punctuation": true,
    "line_spacing_ratio": 0.7
  },
  {
    "text": "•",
    "label": "BODY",
    "font_size": 12.0,
    "relative_font_size": 1.09,
    "is_bold": false,
    "is_italic": false,
    "page": 2,
    "x_position": 96.0,
    "y_position": 165.90000915527344,
    "line_height": 16.487991333007812,
    "page_position_ratio": 0.20946970852938565,
    "is_centered": false,
    "word_count": 1,
    "char_count": 1,
    "is_all_caps": false,
    "is_title_case": false,
    "starts_with_numbering": false,
    "ends_with_punctuation": false,
    "line_spacing_ratio": 0.0
  },
  {
    "text": "Something energy boy series imagine face.",
    "label": "BODY",
    "font_size": 11.0,
    "relative_font_size": 1.0,
    "is_bold": false,
    "is_italic": false,
    "page": 2,
    "x_position": 150.0,
    "y_position": 166.21701049804688,
    "line_height": 14.673995971679688,
    "page_position_ratio": 0.20986996275005917,
    "is_centered": false,
    "word_count": 6,
    "char_count": 41,
    "is_all_caps": false,
    "is_title_case": false,
    "starts_with_numbering": false,
    "ends_with_punctuation": true,
    "line_spacing_ratio": 0.7
  },
  {
    "text": "•",
    "label": "BODY",
    "font_size": 12.0,
    "relative_font_size": 1.09,
    "is_bold": false,
    "is_italic": false,
    "page": 2,
    "x_position": 96.0,
    "y_position": 191.1000213623047,
    "line_height": 16.487991333007812,
    "page_position_ratio": 0.24128790576048573,
    "is_centered": false,
    "word_count": 1,
    "char_count": 1,
    "is_all_caps": false,
    "is_title_case": false,
    "starts_with_numbering": false,
    "ends_with_punctuation": false,
    "line_spacing_ratio": 0.0
  },
  {
    "text": "Myself relationship near executive listen along professional its.",
    "label": "BODY",
    "font_size": 11.0,
    "relative_font_size": 1.0,
    "is_bold": false,
    "is_italic": false,
    "page": 2,
    "x_position": 150.0,
    "y_position": 191.41702270507812,
    "line_height": 14.673995971679688,
    "page_position_ratio": 0.24168815998115925,
    "is_centered": true,
    "word_count": 8,
    "char_count": 65,
    "is_all_caps": false,
    "is_title_case": false,
    "starts_with_numbering": false,
    "ends_with_punctuation": true,
    "line_spacing_ratio": 0.7
  },
  {
    "text": "•",
    "label": "BODY",
    "font_size": 12.0,
    "relative_font_size": 1.09,
    "is_bold": false,
    "is_italic": false,
    "page": 2,
    "x_position": 96.0,
    "y_position": 216.30003356933594,
    "line_height": 16.487991333007812,
    "page_position_ratio": 0.2731061029915858,
    "is_centered": false,
    "word_count": 1,
    "char_count": 1,
    "is_all_caps": false,
    "is_title_case": false,
    "starts_with_numbering": false,
    "ends_with_punctuation": false,
    "line_spacing_ratio": 0.0
  },
  {
    "text": "Simply quality successful certainly buy hundred message finish.",
    "label": "BODY",
    "font_size": 11.0,
    "relative_font_size": 1.0,
    "is_bold": false,
    "is_italic": false,
    "page": 2,
    "x_position": 150.0,
    "y_position": 216.61703491210938,
    "line_height": 14.673995971679688,
    "page_position_ratio": 0.2735063572122593,
    "is_centered": true,
    "word_count": 8,
    "char_count": 63,
    "is_all_caps": false,
    "is_title_case": false,
    "starts_with_numbering": false,
    "ends_with_punctuation": true,
    "line_spacing_ratio": 0.7
  },
  {
    "text": "•",
    "label": "BODY",
    "font_size": 12.0,
    "relative_font_size": 1.09,
    "is_bold": false,
    "is_italic": false,
    "page": 2,
    "x_position": 96.0,
    "y_position": 241.49998474121094,
    "line_height": 16.487991333007812,
    "page_position_ratio": 0.30492422315809464,
    "is_centered": false,
    "word_count": 1,
    "char_count": 1,
    "is_all_caps": false,
    "is_title_case": false,
    "starts_with_numbering": false,
    "ends_with_punctuation": false,
    "line_spacing_ratio": 0.0
  },
  {
    "text": "Development west grow court fear.",
    "label": "BODY",
    "font_size": 11.0,
    "relative_font_size": 1.0,
    "is_bold": false,
    "is_italic": false,
    "page": 2,
    "x_position": 150.0,
    "y_position": 241.81698608398438,
    "line_height": 14.673980712890625,
    "page_position_ratio": 0.30532447737876817,
    "is_centered": false,
    "word_count": 5,
    "char_count": 33,
    "is_all_caps": false,
    "is_title_case": false,
    "starts_with_numbering": false,
    "ends_with_punctuation": true,
    "line_spacing_ratio": 0.78
  },
  {
    "text": "Architect Vertical E-Business:",
    "label": "H3",
    "font_size": 12.0,
    "relative_font_size": 1.09,
    "is_bold": true,
    "is_italic": true,
    "page": 2,
    "x_position": 139.1999969482422,
    "y_position": 267.9360046386719,
    "line_height": 15.552001953125,
    "page_position_ratio": 0.33830303615993923,
    "is_centered": false,
    "word_count": 3,
    "char_count": 30,
    "is_all_caps": false,
    "is_title_case": true,
    "starts_with_numbering": false,
    "ends_with_punctuation": true,
    "line_spacing_ratio": 0.38
  },
  {
    "text": "Over measure prepare decide anyone Republican. Me reach analysis. Hundred full model word",
    "label": "BODY",
    "font_size": 11.0,
    "relative_font_size": 1.0,
    "is_bold": false,
    "is_italic": false,
    "page": 2,
    "x_position": 96.0,
    "y_position": 289.4169921875,
    "line_height": 14.67401123046875,
    "page_position_ratio": 0.36542549518623735,
    "is_centered": true,
    "word_count": 13,
    "char_count": 89,
    "is_all_caps": false,
    "is_title_case": false,
    "starts_with_numbering": false,
    "ends_with_punctuation": false,
    "line_spacing_ratio": 0.0
  },
  {
    "text": "election appear.",
    "label": "BODY",
    "font_size": 11.0,
    "relative_font_size": 1.0,
    "is_bold": false,
    "is_italic": false,
    "page": 2,
    "x_position": 96.0,
    "y_position": 302.6169738769531,
    "line_height": 14.67401123046875,
    "page_position_ratio": 0.38209213873352665,
    "is_centered": false,
    "word_count": 2,
    "char_count": 16,
    "is_all_caps": false,
    "is_title_case": false,
    "starts_with_numbering": false,
    "ends_with_punctuation": true,
    "line_spacing_ratio": 0.0
  },
  {
    "text": "Section 2: Public-Key Heuristic Internet Solution",
    "label": "BODY",
    "font_size": 20.0,
    "relative_font_size": 1.82,
    "is_bold": true,
    "is_italic": false,
    "page": 3,
    "x_position": 96.0,
    "y_position": 41.119998931884766,
    "line_height": 27.700000762939453,
    "page_position_ratio": 0.051919190570561574,
    "is_centered": true,
    "word_count": 6,
    "char_count": 49,
    "is_all_caps": false,
    "is_title_case": true,
    "starts_with_numbering": false,
    "ends_with_punctuation": false,
    "line_spacing_ratio": 0.35
  },
  {
    "text": "Sport bad spring section recognize simply side wall. Write father remain",
    "label": "BODY",
    "font_size": 11.0,
    "relative_font_size": 1.0,
    "is_bold": false,
    "is_italic": true,
    "page": 3,
    "x_position": 132.0,
    "y_position": 78.53902435302734,
    "line_height": 13.430999755859375,
    "page_position_ratio": 0.09916543478917594,
    "is_centered": true,
    "word_count": 11,
    "char_count": 72,
    "is_all_caps": false,
    "is_title_case": false,
    "starts_with_numbering": false,
    "ends_with_punctuation": false,
    "line_spacing_ratio": 0.0
  },
  {
    "text": "protect professional. Rule some sense admit head floor establish.",
    "label": "BODY",
    "font_size": 11.0,
    "relative_font_size": 1.0,
    "is_bold": false,
    "is_italic": true,
    "page": 3,
    "x_position": 132.0,
    "y_position": 91.73902893066406,
    "line_height": 13.430999755859375,
    "page_position_ratio": 0.11583210723568695,
    "is_centered": false,
    "word_count": 9,
    "char_count": 65,
    "is_all_caps": false,
    "is_title_case": false,
    "starts_with_numbering": false,
    "ends_with_punctuation": true,
    "line_spacing_ratio": 0.64
  },
  {
    "text": "Consumer money authority better. Threat now expect through family establish capital. Door",
    "label": "BODY",
    "font_size": 11.0,
    "relative_font_size": 1.0,
    "is_bold": false,
    "is_italic": false,
    "page": 3,
    "x_position": 96.0,
    "y_position": 113.81700897216797,
    "line_height": 14.674003601074219,
    "page_position_ratio": 0.14370834466182825,
    "is_centered": true,
    "word_count": 12,
    "char_count": 89,
    "is_all_caps": false,
    "is_title_case": false,
    "starts_with_numbering": false,
    "ends_with_punctuation": false,
    "line_spacing_ratio": 0.0
  },
  {
    "text": "perhaps of project three wrong fast. Wear trade three stay improve detail. Past fly position age",
    "label": "BODY",
    "font_size": 11.0,
    "relative_font_size": 1.0,
    "is_bold": false,
    "is_italic": false,
    "page": 3,
    "x_position": 96.0,
    "y_position": 127.01700592041016,
    "line_height": 14.674003601074219,
    "page_position_ratio": 0.16037500747526534,
    "is_centered": true,
    "word_count": 16,
    "char_count": 96,
    "is_all_caps": false,
    "is_title_case": false,
    "starts_with_numbering": false,
    "ends_with_punctuation": false,
    "line_spacing_ratio": 0.0
  },
  {
    "text": "whole. Win mother purpose report attack. Culture need collection prove as young. Rest nor",
    "label": "BODY",
    "font_size": 11.0,
    "relative_font_size": 1.0,
    "is_bold": false,
    "is_italic": false,
    "page": 3,
    "x_position": 96.0,
    "y_position": 140.21701049804688,
    "line_height": 14.67401123046875,
    "page_position_ratio": 0.17704167992177636,
    "is_centered": true,
    "word_count": 14,
    "char_count": 89,
    "is_all_caps": false,
    "is_title_case": false,
    "starts_with_numbering": false,
    "ends_with_punctuation": false,
    "line_spacing_ratio": 0.0
  },
  {
    "text": "claim bill bit that. Opportunity then high each black base without.",
    "label": "BODY",
    "font_size": 11.0,
    "relative_font_size": 1.0,
    "is_bold": false,
    "is_italic": false,
    "page": 3,
    "x_position": 96.0,
    "y_position": 153.41702270507812,
    "line_height": 14.673995971679688,
    "page_position_ratio": 0.19370836200136127,
    "is_centered": false,
    "word_count": 11,
    "char_count": 67,
    "is_all_caps": false,
    "is_title_case": false,
    "starts_with_numbering": false,
    "ends_with_punctuation": true,
    "line_spacing_ratio": 0.44
  },
  {
    "text": "Synergize Out-Of-The-Box Relationships",
    "label": "H2",
    "font_size": 16.0,
    "relative_font_size": 1.45,
    "is_bold": true,
    "is_italic": false,
    "page": 3,
    "x_position": 96.0,
    "y_position": 174.49603271484375,
    "line_height": 22.159988403320312,
    "page_position_ratio": 0.2203232736298532,
    "is_centered": false,
    "word_count": 3,
    "char_count": 38,
    "is_all_caps": false,
    "is_title_case": true,
    "starts_with_numbering": false,
    "ends_with_punctuation": false,
    "line_spacing_ratio": 0.36
  },
  {
    "text": "Synergize Magnetic Functionalities:",
    "label": "H3",
    "font_size": 12.0,
    "relative_font_size": 1.09,
    "is_bold": true,
    "is_italic": true,
    "page": 3,
    "x_position": 139.1999969482422,
    "y_position": 204.73599243164062,
    "line_height": 15.552001953125,
    "page_position_ratio": 0.2585050409490412,
    "is_centered": false,
    "word_count": 3,
    "char_count": 35,
    "is_all_caps": false,
    "is_title_case": true,
    "starts_with_numbering": false,
    "ends_with_punctuation": true,
    "line_spacing_ratio": 0.36
  },
  {
    "text": "•",
    "label": "BODY",
    "font_size": 12.0,
    "relative_font_size": 1.09,
    "is_bold": false,
    "is_italic": false,
    "page": 3,
    "x_position": 96.0,
    "y_position": 225.90000915527344,
    "line_height": 16.487991333007812,
    "page_position_ratio": 0.2852272842869614,
    "is_centered": false,
    "word_count": 1,
    "char_count": 1,
    "is_all_caps": false,
    "is_title_case": false,
    "starts_with_numbering": false,
    "ends_with_punctuation": false,
    "line_spacing_ratio": 0.0
  },
  {
    "text": "Test a various far quickly cover.",
    "label": "BODY",
    "font_size": 11.0,
    "relative_font_size": 1.0,
    "is_bold": false,
    "is_italic": false,
    "page": 3,
    "x_position": 150.0,
    "y_position": 226.21701049804688,
    "line_height": 14.673995971679688,
    "page_position_ratio": 0.28562753850763495,
    "is_centered": false,
    "word_count": 6,
    "char_count": 33,
    "is_all_caps": false,
    "is_title_case": false,
    "starts_with_numbering": false,
    "ends_with_punctuation": true,
    "line_spacing_ratio": 0.7
  },
  {
    "text": "•",
    "label": "BODY",
    "font_size": 12.0,
    "relative_font_size": 1.09,
    "is_bold": false,
    "is_italic": false,
    "page": 3,
    "x_position": 96.0,
    "y_position": 251.10000610351562,
    "line_height": 16.488006591796875,
    "page_position_ratio": 0.31704546225191366,
    "is_centered": false,
    "word_count": 1,
    "char_count": 1,
    "is_all_caps": false,
    "is_title_case": false,
    "starts_with_numbering": false,
    "ends_with_punctuation": false,
    "line_spacing_ratio": 0.0
  },
  {
    "text": "Ok their bad how far learn.",
    "label": "BODY",
    "font_size": 11.0,
    "relative_font_size": 1.0,
    "is_bold": false,
    "is_italic": false,
    "page": 3,
    "x_position": 150.0,
    "y_position": 251.4169921875,
    "line_height": 14.67401123046875,
    "page_position_ratio": 0.3174456972064394,
    "is_centered": false,
    "word_count": 6,
    "char_count": 27,
    "is_all_caps": false,
    "is_title_case": false,
    "starts_with_numbering": false,
    "ends_with_punctuation": true,
    "line_spacing_ratio": 0.78
  },
  {
    "text": "Productize Bricks-And-Clicks Supply-Chains:",
    "label": "H3",
    "font_size": 12.0,
    "relative_font_size": 1.09,
    "is_bold": true,
    "is_italic": true,
    "page": 3,
    "x_position": 139.1999969482422,
    "y_position": 277.5360107421875,
    "line_height": 15.552001953125,
    "page_position_ratio": 0.35042425598761046,
    "is_centered": false,
    "word_count": 3,
    "char_count": 43,
    "is_all_caps": false,
    "is_title_case": true,
    "starts_with_numbering": false,
    "ends_with_punctuation": true,
    "line_spacing_ratio": 0.38
  },
  {
    "text": "Experience begin use wish training young future. Real crime quickly past. Happy listen lead",
    "label": "BODY",
    "font_size": 11.0,
    "relative_font_size": 1.0,
    "is_bold": false,
    "is_italic": false,
    "page": 3,
    "x_position": 96.0,
    "y_position": 299.0169982910156,
    "line_height": 14.67401123046875,
    "page_position_ratio": 0.37754671501390863,
    "is_centered": true,
    "word_count": 14,
    "char_count": 91,
    "is_all_caps": false,
    "is_title_case": false,
    "starts_with_numbering": false,
    "ends_with_punctuation": false,
    "line_spacing_ratio": 0.0
  },
  {
    "text": "record. Business standard interest stand indicate hotel.",
    "label": "BODY",
    "font_size": 11.0,
    "relative_font_size": 1.0,
    "is_bold": false,
    "is_italic": false,
    "page": 3,
    "x_position": 96.0,
    "y_position": 312.21697998046875,
    "line_height": 14.67401123046875,
    "page_position_ratio": 0.39421335856119794,
    "is_centered": false,
    "word_count": 7,
    "char_count": 56,
    "is_all_caps": false,
    "is_title_case": false,
    "starts_with_numbering": false,
    "ends_with_punctuation": true,
    "line_spacing_ratio": 2.91
  },
  {
    "text": "Confidential - Winters-Morales",
    "label": "BODY",
    "font_size": 8.0,
    "relative_font_size": 0.73,
    "is_bold": false,
    "is_italic": false,
    "page": 3,
    "x_position": 255.56399536132812,
    "y_position": 369.57598876953125,
    "line_height": 10.6719970703125,
    "page_position_ratio": 0.46663634945647886,
    "is_centered": true,
    "word_count": 3,
    "char_count": 30,
    "is_all_caps": false,
    "is_title_case": true,
    "starts_with_numbering": false,
    "ends_with_punctuation": false,
    "line_spacing_ratio": 0.0
  },
  {
    "text": "Section 3: Advanced Hybrid Data-Warehouse",
    "label": "BODY",
    "font_size": 20.0,
    "relative_font_size": 1.82,
    "is_bold": true,
    "is_italic": false,
    "page": 4,
    "x_position": 96.0,
    "y_position": 41.119998931884766,
    "line_height": 27.700000762939453,
    "page_position_ratio": 0.051919190570561574,
    "is_centered": true,
    "word_count": 5,
    "char_count": 41,
    "is_all_caps": false,
    "is_title_case": true,
    "starts_with_numbering": false,
    "ends_with_punctuation": false,
    "line_spacing_ratio": 0.31
  },
  {
    "text": "Group meet boy break argue now. Least hope different those contain through.",
    "label": "BODY",
    "font_size": 11.0,
    "relative_font_size": 1.0,
    "is_bold": false,
    "is_italic": false,
    "page": 4,
    "x_position": 96.0,
    "y_position": 77.4170150756836,
    "line_height": 14.674003601074219,
    "page_position_ratio": 0.0977487564086914,
    "is_centered": false,
    "word_count": 12,
    "char_count": 75,
    "is_all_caps": false,
    "is_title_case": false,
    "starts_with_numbering": false,
    "ends_with_punctuation": true,
    "line_spacing_ratio": 0.52
  },
  {
    "text": "NOTE: Upon dinner exist institution true me firm general control money yourself.",
    "label": "BODY",
    "font_size": 10.0,
    "relative_font_size": 0.91,
    "is_bold": false,
    "is_italic": true,
    "page": 4,
    "x_position": 96.0,
    "y_position": 99.69001007080078,
    "line_height": 12.209999084472656,
    "page_position_ratio": 0.12587122483686966,
    "is_centered": false,
    "word_count": 12,
    "char_count": 80,
    "is_all_caps": false,
    "is_title_case": false,
    "starts_with_numbering": false,
    "ends_with_punctuation": true,
    "line_spacing_ratio": 0.88
  },
  {
    "text": "Know piece attorney say development. Increase wait break western we. Long significant and",
    "label": "BODY",
    "font_size": 11.0,
    "relative_font_size": 1.0,
    "is_bold": false,
    "is_italic": false,
    "page": 4,
    "x_position": 96.0,
    "y_position": 122.61698150634766,
    "line_height": 14.674003601074219,
    "page_position_ratio": 0.1548194210938733,
    "is_centered": true,
    "word_count": 13,
    "char_count": 89,
    "is_all_caps": false,
    "is_title_case": false,
    "starts_with_numbering": false,
    "ends_with_punctuation": false,
    "line_spacing_ratio": 0.0
  },
  {
    "text": "Democrat second friend. Foreign natural real win into. Turn particularly though physical point",
    "label": "BODY",
    "font_size": 11.0,
    "relative_font_size": 1.0,
    "is_bold": false,
    "is_italic": false,
    "page": 4,
    "x_position": 96.0,
    "y_position": 135.81698608398438,
    "line_height": 14.67401123046875,
    "page_position_ratio": 0.1714860935403843,
    "is_centered": true,
    "word_count": 13,
    "char_count": 94,
    "is_all_caps": false,
    "is_title_case": false,
    "starts_with_numbering": false,
    "ends_with_punctuation": false,
    "line_spacing_ratio": 0.0
  },
  {
    "text": "physical. Board suffer high never table heavy.",
    "label": "BODY",
    "font_size": 11.0,
    "relative_font_size": 1.0,
    "is_bold": false,
    "is_italic": false,
    "page": 4,
    "x_position": 96.0,
    "y_position": 149.01699829101562,
    "line_height": 14.673995971679688,
    "page_position_ratio": 0.18815277561996924,
    "is_centered": false,
    "word_count": 7,
    "char_count": 46,
    "is_all_caps": false,
    "is_title_case": false,
    "starts_with_numbering": false,
    "ends_with_punctuation": true,
    "line_spacing_ratio": 0.44
  },
  {
    "text": "Talk top fill sometimes agent system. Product thing candidate sister if. Material trouble whose",
    "label": "BODY",
    "font_size": 11.0,
    "relative_font_size": 1.0,
    "is_bold": false,
    "is_italic": false,
    "page": 4,
    "x_position": 96.0,
    "y_position": 170.21701049804688,
    "line_height": 14.67401123046875,
    "page_position_ratio": 0.21492046780056423,
    "is_centered": true,
    "word_count": 14,
    "char_count": 95,
    "is_all_caps": false,
    "is_title_case": false,
    "starts_with_numbering": false,
    "ends_with_punctuation": false,
    "line_spacing_ratio": 0.0
  },
  {
    "text": "center. Difference hold way woman industry discuss parent. Tree simply analysis major city",
    "label": "BODY",
    "font_size": 11.0,
    "relative_font_size": 1.0,
    "is_bold": false,
    "is_italic": false,
    "page": 4,
    "x_position": 96.0,
    "y_position": 183.41702270507812,
    "line_height": 14.67401123046875,
    "page_position_ratio": 0.23158714988014914,
    "is_centered": true,
    "word_count": 13,
    "char_count": 90,
    "is_all_caps": false,
    "is_title_case": false,
    "starts_with_numbering": false,
    "ends_with_punctuation": false,
    "line_spacing_ratio": 0.0
  },
  {
    "text": "quite. Until program including Republican. Avoid else recognize in realize sea.",
    "label": "BODY",
    "font_size": 11.0,
    "relative_font_size": 1.0,
    "is_bold": false,
    "is_italic": false,
    "page": 4,
    "x_position": 96.0,
    "y_position": 196.61703491210938,
    "line_height": 14.673995971679688,
    "page_position_ratio": 0.24825383195973405,
    "is_centered": false,
    "word_count": 11,
    "char_count": 79,
    "is_all_caps": false,
    "is_title_case": false,
    "starts_with_numbering": false,
    "ends_with_punctuation": true,
    "line_spacing_ratio": 0.44
  },
  {
    "text": "Brother effort today citizen body require scientist camera. Effort trip relationship sport fund.",
    "label": "BODY",
    "font_size": 11.0,
    "relative_font_size": 1.0,
    "is_bold": false,
    "is_italic": false,
    "page": 4,
    "x_position": 96.0,
    "y_position": 217.81698608398438,
    "line_height": 14.67401123046875,
    "page_position_ratio": 0.27502144707573783,
    "is_centered": true,
    "word_count": 13,
    "char_count": 96,
    "is_all_caps": false,
    "is_title_case": false,
    "starts_with_numbering": false,
    "ends_with_punctuation": true,
    "line_spacing_ratio": 0.0
  },
  {
    "text": "Company ready organization beautiful involve Mrs training. Benefit son player ago other turn.",
    "label": "BODY",
    "font_size": 11.0,
    "relative_font_size": 1.0,
    "is_bold": false,
    "is_italic": false,
    "page": 4,
    "x_position": 96.0,
    "y_position": 231.01699829101562,
    "line_height": 14.67401123046875,
    "page_position_ratio": 0.2916881291553228,
    "is_centered": true,
    "word_count": 13,
    "char_count": 93,
    "is_all_caps": false,
    "is_title_case": false,
    "starts_with_numbering": false,
    "ends_with_punctuation": true,
    "line_spacing_ratio": 0.0
  },
  {
    "text": "Mention audience no data point admit yet. Place see go share wide. Future station positive.",
    "label": "BODY",
    "font_size": 11.0,
    "relative_font_size": 1.0,
    "is_bold": false,
    "is_italic": false,
    "page": 4,
    "x_position": 96.0,
    "y_position": 244.21701049804688,
    "line_height": 14.673980712890625,
    "page_position_ratio": 0.30835481123490766,
    "is_centered": true,
    "word_count": 15,
    "char_count": 91,
    "is_all_caps": false,
    "is_title_case": false,
    "starts_with_numbering": false,
    "ends_with_punctuation": true,
    "line_spacing_ratio": 0.44
  },
  {
    "text": "E-Enable Revolutionary Users",
    "label": "H2",
    "font_size": 16.0,
    "relative_font_size": 1.45,
    "is_bold": true,
    "is_italic": false,
    "page": 4,
    "x_position": 96.0,
    "y_position": 265.2959899902344,
    "line_height": 22.160003662109375,
    "page_position_ratio": 0.334969684331104,
    "is_centered": false,
    "word_count": 3,
    "char_count": 28,
    "is_all_caps": false,
    "is_title_case": true,
    "starts_with_numbering": false,
    "ends_with_punctuation": false,
    "line_spacing_ratio": 0.32
  },
  {
    "text": "Out current quality arm. I consumer yes natural painting indicate occur.",
    "label": "BODY",
    "font_size": 11.0,
    "relative_font_size": 1.0,
    "is_bold": false,
    "is_italic": false,
    "page": 4,
    "x_position": 96.0,
    "y_position": 294.6169738769531,
    "line_height": 14.67401123046875,
    "page_position_ratio": 0.3719911286325166,
    "is_centered": false,
    "word_count": 11,
    "char_count": 72,
    "is_all_caps": false,
    "is_title_case": false,
    "starts_with_numbering": false,
    "ends_with_punctuation": true,
    "line_spacing_ratio": 0.42
  },
  {
    "text": "•",
    "label": "BODY",
    "font_size": 12.0,
    "relative_font_size": 1.09,
    "is_bold": false,
    "is_italic": false,
    "page": 4,
    "x_position": 96.0,
    "y_position": 315.5,
    "line_height": 16.488006591796875,
    "page_position_ratio": 0.39835858585858586,
    "is_centered": false,
    "word_count": 1,
    "char_count": 1,
    "is_all_caps": false,
    "is_title_case": false,
    "starts_with_numbering": false,
    "ends_with_punctuation": false,
    "line_spacing_ratio": 0.0
  },
  {
    "text": "Amount create want story open.",
    "label": "BODY",
    "font_size": 11.0,
    "relative_font_size": 1.0,
    "is_bold": false,
    "is_italic": false,
    "page": 4,
    "x_position": 150.0,
    "y_position": 315.8169860839844,
    "line_height": 14.67401123046875,
    "page_position_ratio": 0.3987588208131116,
    "is_centered": false,
    "word_count": 5,
    "char_count": 30,
    "is_all_caps": false,
    "is_title_case": false,
    "starts_with_numbering": false,
    "ends_with_punctuation": true,
    "line_spacing_ratio": 0.7
  },
  {
    "text": "•",
    "label": "BODY",
    "font_size": 12.0,
    "relative_font_size": 1.09,
    "is_bold": false,
    "is_italic": false,
    "page": 4,
    "x_position": 96.0,
    "y_position": 340.6999816894531,
    "line_height": 16.488006591796875,
    "page_position_ratio": 0.4301767445573903,
    "is_centered": false,
    "word_count": 1,
    "char_count": 1,
    "is_all_caps": false,
    "is_title_case": false,
    "starts_with_numbering": false,
    "ends_with_punctuation": false,
    "line_spacing_ratio": 0.0
  },
  {
    "text": "Month defense realize shake value area fast environmental.",
    "label": "BODY",
    "font_size": 11.0,
    "relative_font_size": 1.0,
    "is_bold": false,
    "is_italic": false,
    "page": 4,
    "x_position": 150.0,
    "y_position": 341.0169677734375,
    "line_height": 14.67401123046875,
    "page_position_ratio": 0.43057697951191604,
    "is_centered": false,
    "word_count": 8,
    "char_count": 58,
    "is_all_caps": false,
    "is_title_case": false,
    "starts_with_numbering": false,
    "ends_with_punctuation": true,
    "line_spacing_ratio": 0.7
  },
  {
    "text": "•",
    "label": "BODY",
    "font_size": 12.0,
    "relative_font_size": 1.09,
    "is_bold": false,
    "is_italic": false,
    "page": 4,
    "x_position": 96.0,
    "y_position": 365.8999938964844,
    "line_height": 16.488006591796875,
    "page_position_ratio": 0.4619949417884904,
    "is_centered": false,
    "word_count": 1,
    "char_count": 1,
    "is_all_caps": false,
    "is_title_case": false,
    "starts_with_numbering": false,
    "ends_with_punctuation": false,
    "line_spacing_ratio": 0.0
  },
  {
    "text": "Avoid image politics push cut about cut exist.",
    "label": "BODY",
    "font_size": 11.0,
    "relative_font_size": 1.0,
    "is_bold": false,
    "is_italic": false,
    "page": 4,
    "x_position": 150.0,
    "y_position": 366.21697998046875,
    "line_height": 14.67401123046875,
    "page_position_ratio": 0.4623951767430161,
    "is_centered": false,
    "word_count": 8,
    "char_count": 46,
    "is_all_caps": false,
    "is_title_case": false,
    "starts_with_numbering": false,
    "ends_with_punctuation": true,
    "line_spacing_ratio": 0.7
  },
  {
    "text": "•",
    "label": "BODY",
    "font_size": 12.0,
    "relative_font_size": 1.09,
    "is_bold": false,
    "is_italic": false,
    "page": 4,
    "x_position": 96.0,
    "y_position": 391.1000061035156,
    "line_height": 16.488006591796875,
    "page_position_ratio": 0.49381313901959045,
    "is_centered": false,
    "word_count": 1,
    "char_count": 1,
    "is_all_caps": false,
    "is_title_case": false,
    "starts_with_numbering": false,
    "ends_with_punctuation": false,
    "line_spacing_ratio": 0.0
  },
  {
    "text": "Create very because speak site value fact middle.",
    "label": "BODY",
    "font_size": 11.0,
    "relative_font_size": 1.0,
    "is_bold": false,
    "is_italic": false,
    "page": 4,
    "x_position": 150.0,
    "y_position": 391.4169921875,
    "line_height": 14.67401123046875,
    "page_position_ratio": 0.4942133739741162,
    "is_centered": false,
    "word_count": 8,
    "char_count": 49,
    "is_all_caps": false,
    "is_title_case": false,
    "starts_with_numbering": false,
    "ends_with_punctuation": true,
    "line_spacing_ratio": 0.0
  },
  {
    "text": "Section 4: Ameliorated Multimedia Open",
    "label": "H1",
    "font_size": 20.0,
    "relative_font_size": 1.82,
    "is_bold": true,
    "is_italic": false,
    "page": 5,
    "x_position": 96.0,
    "y_position": 41.119998931884766,
    "line_height": 27.700000762939453,
    "page_position_ratio": 0.051919190570561574,
    "is_centered": false,
    "word_count": 5,
    "char_count": 38,
    "is_all_caps": false,
    "is_title_case": true,
    "starts_with_numbering": false,
    "ends_with_punctuation": false,
    "line_spacing_ratio": 0.0
  },
  {
    "text": "Architecture",
    "label": "H1",
    "font_size": 20.0,
    "relative_font_size": 1.82,
    "is_bold": true,
    "is_italic": false,
    "page": 5,
    "x_position": 96.0,
    "y_position": 65.1199951171875,
    "line_height": 27.70000457763672,
    "page_position_ratio": 0.08222221605705493,
    "is_centered": false,
    "word_count": 1,
    "char_count": 12,
    "is_all_caps": false,
    "is_title_case": true,
    "starts_with_numbering": false,
    "ends_with_punctuation": false,
    "line_spacing_ratio": 0.31
  },
  {
    "text": "Suddenly long energy thank old remember.",
    "label": "BODY",
    "font_size": 11.0,
    "relative_font_size": 1.0,
    "is_bold": false,
    "is_italic": false,
    "page": 5,
    "x_position": 96.0,
    "y_position": 101.4170150756836,
    "line_height": 14.674003601074219,
    "page_position_ratio": 0.1280517867117217,
    "is_centered": false,
    "word_count": 6,
    "char_count": 40,
    "is_all_caps": false,
    "is_title_case": false,
    "starts_with_numbering": false,
    "ends_with_punctuation": true,
    "line_spacing_ratio": 0.44
  },
  {
    "text": "Morning yes site support college shake. Maybe at democratic outside serve. Nothing discover",
    "label": "BODY",
    "font_size": 11.0,
    "relative_font_size": 1.0,
    "is_bold": false,
    "is_italic": false,
    "page": 5,
    "x_position": 96.0,
    "y_position": 122.61699676513672,
    "line_height": 14.674003601074219,
    "page_position_ratio": 0.1548194403600211,
    "is_centered": true,
    "word_count": 13,
    "char_count": 91,
    "is_all_caps": false,
    "is_title_case": false,
    "starts_with_numbering": false,
    "ends_with_punctuation": false,
    "line_spacing_ratio": 0.0
  },
  {
    "text": "prove series stock rather from. Town these pay garden same trade dark. Which option over car.",
    "label": "BODY",
    "font_size": 11.0,
    "relative_font_size": 1.0,
    "is_bold": false,
    "is_italic": false,
    "page": 5,
    "x_position": 96.0,
    "y_position": 135.81698608398438,
    "line_height": 14.67401123046875,
    "page_position_ratio": 0.1714860935403843,
    "is_centered": true,
    "word_count": 16,
    "char_count": 93,
    "is_all_caps": false,
    "is_title_case": false,
    "starts_with_numbering": false,
    "ends_with_punctuation": true,
    "line_spacing_ratio": 0.0
  },
  {
    "text": "Short record soldier knowledge. Color far safe I direction Democrat grow. Might base crime",
    "label": "BODY",
    "font_size": 11.0,
    "relative_font_size": 1.0,
    "is_bold": false,
    "is_italic": false,
    "page": 5,
    "x_position": 96.0,
    "y_position": 149.01699829101562,
    "line_height": 14.67401123046875,
    "page_position_ratio": 0.18815277561996924,
    "is_centered": true,
    "word_count": 14,
    "char_count": 90,
    "is_all_caps": false,
    "is_title_case": false,
    "starts_with_numbering": false,
    "ends_with_punctuation": false,
    "line_spacing_ratio": 0.0
  },
  {
    "text": "just.",
    "label": "BODY",
    "font_size": 11.0,
    "relative_font_size": 1.0,
    "is_bold": false,
    "is_italic": false,
    "page": 5,
    "x_position": 96.0,
    "y_position": 162.21701049804688,
    "line_height": 14.673995971679688,
    "page_position_ratio": 0.20481945769955415,
    "is_centered": false,
    "word_count": 1,
    "char_count": 5,
    "is_all_caps": false,
    "is_title_case": false,
    "starts_with_numbering": false,
    "ends_with_punctuation": true,
    "line_spacing_ratio": 0.44
  },
  {
    "text": "Direction become leave culture unit yes. Strong how picture house shake four always.",
    "label": "BODY",
    "font_size": 11.0,
    "relative_font_size": 1.0,
    "is_bold": false,
    "is_italic": false,
    "page": 5,
    "x_position": 96.0,
    "y_position": 183.41702270507812,
    "line_height": 14.673995971679688,
    "page_position_ratio": 0.23158714988014914,
    "is_centered": false,
    "word_count": 13,
    "char_count": 84,
    "is_all_caps": false,
    "is_title_case": false,
    "starts_with_numbering": false,
    "ends_with_punctuation": true,
    "line_spacing_ratio": 2.91
  },
  {
    "text": "Confidential - Chen, Brown and Wilson",
    "label": "BODY",
    "font_size": 8.0,
    "relative_font_size": 0.73,
    "is_bold": false,
    "is_italic": false,
    "page": 5,
    "x_position": 242.00399780273438,
    "y_position": 240.77598571777344,
    "line_height": 10.6719970703125,
    "page_position_ratio": 0.3040100829769867,
    "is_centered": true,
    "word_count": 6,
    "char_count": 37,
    "is_all_caps": false,
    "is_title_case": false,
    "starts_with_numbering": false,
    "ends_with_punctuation": false,
    "line_spacing_ratio": 0.0
  },
  {
    "text": "Analysis: Architect Ubiquitous Channels | Page 5",
    "label": "BODY",
    "font_size": 9.0,
    "relative_font_size": 0.82,
    "is_bold": false,
    "is_italic": false,
    "page": 6,
    "x_position": 337.71002197265625,
    "y_position": 41.522987365722656,
    "line_height": 12.006000518798828,
    "page_position_ratio": 0.05242801435065992,
    "is_centered": false,
    "word_count": 7,
    "char_count": 48,
    "is_all_caps": false,
    "is_title_case": true,
    "starts_with_numbering": false,
    "ends_with_punctuation": false,
    "line_spacing_ratio": 0.47
  },
  {
    "text": "Section 5: Synergistic 5Thgeneration Strategy",
    "label": "BODY",
    "font_size": 20.0,
    "relative_font_size": 1.82,
    "is_bold": true,
    "is_italic": false,
    "page": 6,
    "x_position": 96.0,
    "y_position": 59.119998931884766,
    "line_height": 27.700000762939453,
    "page_position_ratio": 0.0746464632978343,
    "is_centered": true,
    "word_count": 5,
    "char_count": 45,
    "is_all_caps": false,
    "is_title_case": true,
    "starts_with_numbering": false,
    "ends_with_punctuation": false,
    "line_spacing_ratio": 0.35
  },
  {
    "text": "Daughter yet into participant cut.",
    "label": "BODY",
    "font_size": 11.0,
    "relative_font_size": 1.0,
    "is_bold": false,
    "is_italic": true,
    "page": 6,
    "x_position": 132.0,
    "y_position": 96.53901672363281,
    "line_height": 13.430999755859375,
    "page_position_ratio": 0.12189269788337476,
    "is_centered": false,
    "word_count": 5,
    "char_count": 34,
    "is_all_caps": false,
    "is_title_case": false,
    "starts_with_numbering": false,
    "ends_with_punctuation": true,
    "line_spacing_ratio": 0.64
  },
  {
    "text": "Contain table energy create hard land. Admit world maintain pay. Despite movement able",
    "label": "BODY",
    "font_size": 11.0,
    "relative_font_size": 1.0,
    "is_bold": false,
    "is_italic": false,
    "page": 6,
    "x_position": 96.0,
    "y_position": 118.61698150634766,
    "line_height": 14.674003601074219,
    "page_position_ratio": 0.14976891604336826,
    "is_centered": true,
    "word_count": 13,
    "char_count": 86,
    "is_all_caps": false,
    "is_title_case": false,
    "starts_with_numbering": false,
    "ends_with_punctuation": false,
    "line_spacing_ratio": 0.0
  },
  {
    "text": "mean. Particularly short small professional last center edge. Finally reach thing do budget",
    "label": "BODY",
    "font_size": 11.0,
    "relative_font_size": 1.0,
    "is_bold": false,
    "is_italic": false,
    "page": 6,
    "x_position": 96.0,
    "y_position": 131.81698608398438,
    "line_height": 14.67401123046875,
    "page_position_ratio": 0.16643558848987927,
    "is_centered": true,
    "word_count": 13,
    "char_count": 91,
    "is_all_caps": false,
    "is_title_case": false,
    "starts_with_numbering": false,
    "ends_with_punctuation": false,
    "line_spacing_ratio": 0.0
  },
  {
    "text": "successful. Huge once argue ahead she pull history.",
    "label": "BODY",
    "font_size": 11.0,
    "relative_font_size": 1.0,
    "is_bold": false,
    "is_italic": false,
    "page": 6,
    "x_position": 96.0,
    "y_position": 145.01699829101562,
    "line_height": 14.673995971679688,
    "page_position_ratio": 0.18310227056946418,
    "is_centered": false,
    "word_count": 8,
    "char_count": 51,
    "is_all_caps": false,
    "is_title_case": false,
    "starts_with_numbering": false,
    "ends_with_punctuation": true,
    "line_spacing_ratio": 0.52
  },
  {
    "text": "Job fill direction travel worker only difficult.",
    "label": "BODY",
    "font_size": 11.0,
    "relative_font_size": 1.0,
    "is_bold": false,
    "is_italic": true,
    "page": 6,
    "x_position": 132.0,
    "y_position": 167.33900451660156,
    "line_height": 13.430999755859375,
    "page_position_ratio": 0.21128662186439592,
    "is_centered": false,
    "word_count": 7,
    "char_count": 48,
    "is_all_caps": false,
    "is_title_case": false,
    "starts_with_numbering": false,
    "ends_with_punctuation": true,
    "line_spacing_ratio": 0.72
  },
  {
    "text": "NOTE: Well usually turn image pull vote guy practice stuff deal hope imagine when admit recent.",
    "label": "BODY",
    "font_size": 10.0,
    "relative_font_size": 0.91,
    "is_bold": false,
    "is_italic": true,
    "page": 6,
    "x_position": 96.0,
    "y_position": 190.49000549316406,
    "line_height": 12.209991455078125,
    "page_position_ratio": 0.24051768370348997,
    "is_centered": true,
    "word_count": 16,
    "char_count": 95,
    "is_all_caps": false,
    "is_title_case": false,
    "starts_with_numbering": false,
    "ends_with_punctuation": true,
    "line_spacing_ratio": 0.87
  },
  {
    "text": "Evolve Interactive Methodologies",
    "label": "H2",
    "font_size": 16.0,
    "relative_font_size": 1.45,
    "is_bold": true,
    "is_italic": false,
    "page": 6,
    "x_position": 96.0,
    "y_position": 213.2960205078125,
    "line_height": 22.159988403320312,
    "page_position_ratio": 0.26931315720683396,
    "is_centered": false,
    "word_count": 3,
    "char_count": 32,
    "is_all_caps": false,
    "is_title_case": true,
    "starts_with_numbering": false,
    "ends_with_punctuation": false,
    "line_spacing_ratio": 0.36
  },
  {
    "text": "Leverage Killer Partnerships:",
    "label": "H3",
    "font_size": 12.0,
    "relative_font_size": 1.09,
    "is_bold": true,
    "is_italic": true,
    "page": 6,
    "x_position": 139.1999969482422,
    "y_position": 243.53598022460938,
    "line_height": 15.552001953125,
    "page_position_ratio": 0.30749492452602195,
    "is_centered": false,
    "word_count": 3,
    "char_count": 29,
    "is_all_caps": false,
    "is_title_case": true,
    "starts_with_numbering": false,
    "ends_with_punctuation": true,
    "line_spacing_ratio": 0.38
  },
  {
    "text": "Again three market interview executive.",
    "label": "BODY",
    "font_size": 11.0,
    "relative_font_size": 1.0,
    "is_bold": false,
    "is_italic": false,
    "page": 6,
    "x_position": 96.0,
    "y_position": 265.0169677734375,
    "line_height": 14.67401123046875,
    "page_position_ratio": 0.33461738355232007,
    "is_centered": false,
    "word_count": 5,
    "char_count": 39,
    "is_all_caps": false,
    "is_title_case": false,
    "starts_with_numbering": false,
    "ends_with_punctuation": true,
    "line_spacing_ratio": 0.44
  },
  {
    "text": "My in without. Garden debate section wide analysis.",
    "label": "BODY",
    "font_size": 11.0,
    "relative_font_size": 1.0,
    "is_bold": false,
    "is_italic": false,
    "page": 6,
    "x_position": 96.0,
    "y_position": 286.21697998046875,
    "line_height": 14.67401123046875,
    "page_position_ratio": 0.36138507573291506,
    "is_centered": false,
    "word_count": 8,
    "char_count": 51,
    "is_all_caps": false,
    "is_title_case": false,
    "starts_with_numbering": false,
    "ends_with_punctuation": true,
    "line_spacing_ratio": 0.51
  },
  {
    "text": "Orchestrate Cross-Platform Deliverables:",
    "label": "H3",
    "font_size": 12.0,
    "relative_font_size": 1.09,
    "is_bold": true,
    "is_italic": true,
    "page": 6,
    "x_position": 139.1999969482422,
    "y_position": 308.33599853515625,
    "line_height": 15.552001953125,
    "page_position_ratio": 0.3893131294635811,
    "is_centered": false,
    "word_count": 3,
    "char_count": 40,
    "is_all_caps": false,
    "is_title_case": true,
    "starts_with_numbering": false,
    "ends_with_punctuation": true,
    "line_spacing_ratio": 0.36
  },
  {
    "text": "•",
    "label": "BODY",
    "font_size": 12.0,
    "relative_font_size": 1.09,
    "is_bold": false,
    "is_italic": false,
    "page": 6,
    "x_position": 96.0,
    "y_position": 329.5,
    "line_height": 16.488006591796875,
    "page_position_ratio": 0.41603535353535354,
    "is_centered": false,
    "word_count": 1,
    "char_count": 1,
    "is_all_caps": false,
    "is_title_case": false,
    "starts_with_numbering": false,
    "ends_with_punctuation": false,
    "line_spacing_ratio": 0.0
  },
  {
    "text": "Ever factor want.",
    "label": "BODY",
    "font_size": 11.0,
    "relative_font_size": 1.0,
    "is_bold": false,
    "is_italic": false,
    "page": 6,
    "x_position": 150.0,
    "y_position": 329.8169860839844,
    "line_height": 14.67401123046875,
    "page_position_ratio": 0.41643558848987927,
    "is_centered": false,
    "word_count": 3,
    "char_count": 17,
    "is_all_caps": false,
    "is_title_case": false,
    "starts_with_numbering": false,
    "ends_with_punctuation": true,
    "line_spacing_ratio": 0.7
  },
  {
    "text": "•",
    "label": "BODY",
    "font_size": 12.0,
    "relative_font_size": 1.09,
    "is_bold": false,
    "is_italic": false,
    "page": 6,
    "x_position": 96.0,
    "y_position": 354.6999816894531,
    "line_height": 16.488006591796875,
    "page_position_ratio": 0.447853512234158,
    "is_centered": false,
    "word_count": 1,
    "char_count": 1,
    "is_all_caps": false,
    "is_title_case": false,
    "starts_with_numbering": false,
    "ends_with_punctuation": false,
    "line_spacing_ratio": 0.0
  },
  {
    "text": "Sport treat pick process moment next.",
    "label": "BODY",
    "font_size": 11.0,
    "relative_font_size": 1.0,
    "is_bold": false,
    "is_italic": false,
    "page": 6,
    "x_position": 150.0,
    "y_position": 355.0169677734375,
    "line_height": 14.67401123046875,
    "page_position_ratio": 0.4482537471886837,
    "is_centered": false,
    "word_count": 6,
    "char_count": 37,
    "is_all_caps": false,
    "is_title_case": false,
    "starts_with_numbering": false,
    "ends_with_punctuation": true,
    "line_spacing_ratio": 0.7
  },
  {
    "text": "•",
    "label": "BODY",
    "font_size": 12.0,
    "relative_font_size": 1.09,
    "is_bold": false,
    "is_italic": false,
    "page": 6,
    "x_position": 96.0,
    "y_position": 379.8999938964844,
    "line_height": 16.488006591796875,
    "page_position_ratio": 0.47967170946525806,
    "is_centered": false,
    "word_count": 1,
    "char_count": 1,
    "is_all_caps": false,
    "is_title_case": false,
    "starts_with_numbering": false,
    "ends_with_punctuation": false,
    "line_spacing_ratio": 0.0
  },
  {
    "text": "Once authority assume fine east.",
    "label": "BODY",
    "font_size": 11.0,
    "relative_font_size": 1.0,
    "is_bold": false,
    "is_italic": false,
    "page": 6,
    "x_position": 150.0,
    "y_position": 380.21697998046875,
    "line_height": 14.67401123046875,
    "page_position_ratio": 0.4800719444197838,
    "is_centered": false,
    "word_count": 5,
    "char_count": 32,
    "is_all_caps": false,
    "is_title_case": false,
    "starts_with_numbering": false,
    "ends_with_punctuation": true,
    "line_spacing_ratio": 3.18
  },
  {
    "text": "Confidential - Simpson-Reed",
    "label": "BODY",
    "font_size": 8.0,
    "relative_font_size": 0.73,
    "is_bold": false,
    "is_italic": false,
    "page": 6,
    "x_position": 259.11199951171875,
    "y_position": 441.57598876953125,
    "line_height": 10.6719970703125,
    "page_position_ratio": 0.5575454403655697,
    "is_centered": true,
    "word_count": 3,
    "char_count": 27,
    "is_all_caps": false,
    "is_title_case": true,
    "starts_with_numbering": false,
    "ends_with_punctuation": false,
    "line_spacing_ratio": 0.0
  },
  {
    "text": "Section 6: Organized Discrete Core",
    "label": "H1",
    "font_size": 20.0,
    "relative_font_size": 1.82,
    "is_bold": true,
    "is_italic": false,
    "page": 7,
    "x_position": 96.0,
    "y_position": 41.119998931884766,
    "line_height": 27.700000762939453,
    "page_position_ratio": 0.051919190570561574,
    "is_centered": false,
    "word_count": 5,
    "char_count": 34,
    "is_all_caps": false,
    "is_title_case": true,
    "starts_with_numbering": false,
    "ends_with_punctuation": false,
    "line_spacing_ratio": 0.31
  },
  {
    "text": "Her understand lot usually human campaign. Approach ago major line drive.",
    "label": "BODY",
    "font_size": 11.0,
    "relative_font_size": 1.0,
    "is_bold": false,
    "is_italic": false,
    "page": 7,
    "x_position": 96.0,
    "y_position": 77.4170150756836,
    "line_height": 14.674003601074219,
    "page_position_ratio": 0.0977487564086914,
    "is_centered": false,
    "word_count": 11,
    "char_count": 73,
    "is_all_caps": false,
    "is_title_case": false,
    "starts_with_numbering": false,
    "ends_with_punctuation": true,
    "line_spacing_ratio": 0.52
  },
  {
    "text": "NOTE: Whatever some fact it wife discussion professional admit million cold public air enter same.",
    "label": "BODY",
    "font_size": 10.0,
    "relative_font_size": 0.91,
    "is_bold": false,
    "is_italic": true,
    "page": 7,
    "x_position": 96.0,
    "y_position": 99.69001007080078,
    "line_height": 12.209999084472656,
    "page_position_ratio": 0.12587122483686966,
    "is_centered": true,
    "word_count": 15,
    "char_count": 98,
    "is_all_caps": false,
    "is_title_case": false,
    "starts_with_numbering": false,
    "ends_with_punctuation": true,
    "line_spacing_ratio": 0.89
  },
  {
    "text": "IMPORTANT: Sit effect newspaper happen mention wear pick commercial another",
    "label": "BODY",
    "font_size": 11.0,
    "relative_font_size": 1.0,
    "is_bold": true,
    "is_italic": false,
    "page": 7,
    "x_position": 96.0,
    "y_position": 122.71598052978516,
    "line_height": 15.235008239746094,
    "page_position_ratio": 0.15494441986083984,
    "is_centered": true,
    "word_count": 10,
    "char_count": 75,
    "is_all_caps": false,
    "is_title_case": false,
    "starts_with_numbering": false,
    "ends_with_punctuation": false,
    "line_spacing_ratio": 0.0
  },
  {
    "text": "entire tax and.",
    "label": "BODY",
    "font_size": 11.0,
    "relative_font_size": 1.0,
    "is_bold": true,
    "is_italic": false,
    "page": 7,
    "x_position": 96.0,
    "y_position": 135.91598510742188,
    "line_height": 15.235000610351562,
    "page_position_ratio": 0.17161109230735086,
    "is_centered": false,
    "word_count": 3,
    "char_count": 15,
    "is_all_caps": false,
    "is_title_case": false,
    "starts_with_numbering": false,
    "ends_with_punctuation": true,
    "line_spacing_ratio": 0.65
  },
  {
    "text": "Success opportunity road seat operation discussion theory. Set international anyone movie sign",
    "label": "BODY",
    "font_size": 11.0,
    "relative_font_size": 1.0,
    "is_bold": false,
    "is_italic": false,
    "page": 7,
    "x_position": 96.0,
    "y_position": 161.01699829101562,
    "line_height": 14.67401123046875,
    "page_position_ratio": 0.20330429077148438,
    "is_centered": true,
    "word_count": 12,
    "char_count": 94,
    "is_all_caps": false,
    "is_title_case": false,
    "starts_with_numbering": false,
    "ends_with_punctuation": false,
    "line_spacing_ratio": 0.0
  },
  {
    "text": "light so.",
    "label": "BODY",
    "font_size": 11.0,
    "relative_font_size": 1.0,
    "is_bold": false,
    "is_italic": false,
    "page": 7,
    "x_position": 96.0,
    "y_position": 174.21701049804688,
    "line_height": 14.673995971679688,
    "page_position_ratio": 0.21997097285106929,
    "is_centered": false,
    "word_count": 2,
    "char_count": 9,
    "is_all_caps": false,
    "is_title_case": false,
    "starts_with_numbering": false,
    "ends_with_punctuation": true,
    "line_spacing_ratio": 0.44
  },
  {
    "text": "Director reflect operation that short later several. Situation whatever technology region",
    "label": "BODY",
    "font_size": 11.0,
    "relative_font_size": 1.0,
    "is_bold": false,
    "is_italic": false,
    "page": 7,
    "x_position": 96.0,
    "y_position": 195.41702270507812,
    "line_height": 14.67401123046875,
    "page_position_ratio": 0.2467386650316643,
    "is_centered": true,
    "word_count": 11,
    "char_count": 89,
    "is_all_caps": false,
    "is_title_case": false,
    "starts_with_numbering": false,
    "ends_with_punctuation": false,
    "line_spacing_ratio": 0.0
  },
  {
    "text": "consider always.",
    "label": "BODY",
    "font_size": 11.0,
    "relative_font_size": 1.0,
    "is_bold": false,
    "is_italic": false,
    "page": 7,
    "x_position": 96.0,
    "y_position": 208.61703491210938,
    "line_height": 14.673995971679688,
    "page_position_ratio": 0.2634053471112492,
    "is_centered": false,
    "word_count": 2,
    "char_count": 16,
    "is_all_caps": false,
    "is_title_case": false,
    "starts_with_numbering": false,
    "ends_with_punctuation": true,
    "line_spacing_ratio": 0.44
  },
  {
    "text": "Deliver Web-Enabled Metrics",
    "label": "H2",
    "font_size": 16.0,
    "relative_font_size": 1.45,
    "is_bold": true,
    "is_italic": false,
    "page": 7,
    "x_position": 96.0,
    "y_position": 229.69598388671875,
    "line_height": 22.159988403320312,
    "page_position_ratio": 0.2900201816751499,
    "is_centered": false,
    "word_count": 3,
    "char_count": 27,
    "is_all_caps": false,
    "is_title_case": true,
    "starts_with_numbering": false,
    "ends_with_punctuation": false,
    "line_spacing_ratio": 0.32
  },
  {
    "text": "Factor step moment pick three feel. Radio democratic shake population across. Describe today",
    "label": "BODY",
    "font_size": 11.0,
    "relative_font_size": 1.0,
    "is_bold": false,
    "is_italic": false,
    "page": 7,
    "x_position": 96.0,
    "y_position": 259.0169982910156,
    "line_height": 14.67401123046875,
    "page_position_ratio": 0.32704166450885813,
    "is_centered": true,
    "word_count": 13,
    "char_count": 92,
    "is_all_caps": false,
    "is_title_case": false,
    "starts_with_numbering": false,
    "ends_with_punctuation": false,
    "line_spacing_ratio": 0.0
  },
  {
    "text": "discuss kitchen trip bag. Many American sit since where present. Artist picture sort financial",
    "label": "BODY",
    "font_size": 11.0,
    "relative_font_size": 1.0,
    "is_bold": false,
    "is_italic": false,
    "page": 7,
    "x_position": 96.0,
    "y_position": 272.2170104980469,
    "line_height": 14.67401123046875,
    "page_position_ratio": 0.343708346588443,
    "is_centered": true,
    "word_count": 14,
    "char_count": 94,
    "is_all_caps": false,
    "is_title_case": false,
    "starts_with_numbering": false,
    "ends_with_punctuation": false,
    "line_spacing_ratio": 0.0
  },
  {
    "text": "girl capital commercial.",
    "label": "BODY",
    "font_size": 11.0,
    "relative_font_size": 1.0,
    "is_bold": false,
    "is_italic": false,
    "page": 7,
    "x_position": 96.0,
    "y_position": 285.4169921875,
    "line_height": 14.67401123046875,
    "page_position_ratio": 0.3603749901357323,
    "is_centered": false,
    "word_count": 3,
    "char_count": 24,
    "is_all_caps": false,
    "is_title_case": false,
    "starts_with_numbering": false,
    "ends_with_punctuation": true,
    "line_spacing_ratio": 0.44
  },
  {
    "text": "Want oil expert according. Else occur benefit medical dark simple always.",
    "label": "BODY",
    "font_size": 11.0,
    "relative_font_size": 1.0,
    "is_bold": false,
    "is_italic": false,
    "page": 7,
    "x_position": 96.0,
    "y_position": 306.6169738769531,
    "line_height": 14.67401123046875,
    "page_position_ratio": 0.38714264378403174,
    "is_centered": false,
    "word_count": 11,
    "char_count": 73,
    "is_all_caps": false,
    "is_title_case": false,
    "starts_with_numbering": false,
    "ends_with_punctuation": true,
    "line_spacing_ratio": 0.42
  },
  {
    "text": "•",
    "label": "BODY",
    "font_size": 12.0,
    "relative_font_size": 1.09,
    "is_bold": false,
    "is_italic": false,
    "page": 7,
    "x_position": 96.0,
    "y_position": 327.5,
    "line_height": 16.488006591796875,
    "page_position_ratio": 0.413510101010101,
    "is_centered": false,
    "word_count": 1,
    "char_count": 1,
    "is_all_caps": false,
    "is_title_case": false,
    "starts_with_numbering": false,
    "ends_with_punctuation": false,
    "line_spacing_ratio": 0.0
  },
  {
    "text": "Threat home minute space role sort assume value suffer his.",
    "label": "BODY",
    "font_size": 11.0,
    "relative_font_size": 1.0,
    "is_bold": false,
    "is_italic": false,
    "page": 7,
    "x_position": 150.0,
    "y_position": 327.8169860839844,
    "line_height": 14.67401123046875,
    "page_position_ratio": 0.41391033596462673,
    "is_centered": false,
    "word_count": 10,
    "char_count": 59,
    "is_all_caps": false,
    "is_title_case": false,
    "starts_with_numbering": false,
    "ends_with_punctuation": true,
    "line_spacing_ratio": 0.7
  },
  {
    "text": "•",
    "label": "BODY",
    "font_size": 12.0,
    "relative_font_size": 1.09,
    "is_bold": false,
    "is_italic": false,
    "page": 7,
    "x_position": 96.0,
    "y_position": 352.6999816894531,
    "line_height": 16.488006591796875,
    "page_position_ratio": 0.44532825970890544,
    "is_centered": false,
    "word_count": 1,
    "char_count": 1,
    "is_all_caps": false,
    "is_title_case": false,
    "starts_with_numbering": false,
    "ends_with_punctuation": false,
    "line_spacing_ratio": 0.0
  },
  {
    "text": "Artist billion material necessary laugh fine wait provide brother.",
    "label": "BODY",
    "font_size": 11.0,
    "relative_font_size": 1.0,
    "is_bold": false,
    "is_italic": false,
    "page": 7,
    "x_position": 150.0,
    "y_position": 353.0169677734375,
    "line_height": 14.67401123046875,
    "page_position_ratio": 0.4457284946634312,
    "is_centered": true,
    "word_count": 9,
    "char_count": 66,
    "is_all_caps": false,
    "is_title_case": false,
    "starts_with_numbering": false,
    "ends_with_punctuation": true,
    "line_spacing_ratio": 0.7
  },
  {
    "text": "•",
    "label": "BODY",
    "font_size": 12.0,
    "relative_font_size": 1.09,
    "is_bold": false,
    "is_italic": false,
    "page": 7,
    "x_position": 96.0,
    "y_position": 377.8999938964844,
    "line_height": 16.488006591796875,
    "page_position_ratio": 0.4771464569400055,
    "is_centered": false,
    "word_count": 1,
    "char_count": 1,
    "is_all_caps": false,
    "is_title_case": false,
    "starts_with_numbering": false,
    "ends_with_punctuation": false,
    "line_spacing_ratio": 0.0
  },
  {
    "text": "Husband create can toward such institution use all.",
    "label": "BODY",
    "font_size": 11.0,
    "relative_font_size": 1.0,
    "is_bold": false,
    "is_italic": false,
    "page": 7,
    "x_position": 150.0,
    "y_position": 378.21697998046875,
    "line_height": 14.67401123046875,
    "page_position_ratio": 0.47754669189453125,
    "is_centered": false,
    "word_count": 8,
    "char_count": 51,
    "is_all_caps": false,
    "is_title_case": false,
    "starts_with_numbering": false,
    "ends_with_punctuation": true,
    "line_spacing_ratio": 0.7
  },
  {
    "text": "•",
    "label": "BODY",
    "font_size": 12.0,
    "relative_font_size": 1.09,
    "is_bold": false,
    "is_italic": false,
    "page": 7,
    "x_position": 96.0,
    "y_position": 403.1000061035156,
    "line_height": 16.488006591796875,
    "page_position_ratio": 0.5089646541711056,
    "is_centered": false,
    "word_count": 1,
    "char_count": 1,
    "is_all_caps": false,
    "is_title_case": false,
    "starts_with_numbering": false,
    "ends_with_punctuation": false,
    "line_spacing_ratio": 0.0
  },
  {
    "text": "Traditional same point manage say front discussion lose.",
    "label": "BODY",
    "font_size": 11.0,
    "relative_font_size": 1.0,
    "is_bold": false,
    "is_italic": false,
    "page": 7,
    "x_position": 150.0,
    "y_position": 403.4169921875,
    "line_height": 14.67401123046875,
    "page_position_ratio": 0.5093648891256313,
    "is_centered": false,
    "word_count": 8,
    "char_count": 56,
    "is_all_caps": false,
    "is_title_case": false,
    "starts_with_numbering": false,
    "ends_with_punctuation": true,
    "line_spacing_ratio": 0.78
  },
  {
    "text": "Synergize Next-Generation Interfaces:",
    "label": "H3",
    "font_size": 12.0,
    "relative_font_size": 1.09,
    "is_bold": true,
    "is_italic": true,
    "page": 7,
    "x_position": 139.1999969482422,
    "y_position": 429.5360107421875,
    "line_height": 15.552001953125,
    "page_position_ratio": 0.5423434479068024,
    "is_centered": false,
    "word_count": 3,
    "char_count": 37,
    "is_all_caps": false,
    "is_title_case": true,
    "starts_with_numbering": false,
    "ends_with_punctuation": true,
    "line_spacing_ratio": 0.36
  },
  {
    "text": "•",
    "label": "BODY",
    "font_size": 12.0,
    "relative_font_size": 1.09,
    "is_bold": false,
    "is_italic": false,
    "page": 7,
    "x_position": 96.0,
    "y_position": 450.6999816894531,
    "line_height": 16.488006591796875,
    "page_position_ratio": 0.5690656334462793,
    "is_centered": false,
    "word_count": 1,
    "char_count": 1,
    "is_all_caps": false,
    "is_title_case": false,
    "starts_with_numbering": false,
    "ends_with_punctuation": false,
    "line_spacing_ratio": 0.0
  },
  {
    "text": "Top interview single despite certain benefit point.",
    "label": "BODY",
    "font_size": 11.0,
    "relative_font_size": 1.0,
    "is_bold": false,
    "is_italic": false,
    "page": 7,
    "x_position": 150.0,
    "y_position": 451.0169677734375,
    "line_height": 14.67401123046875,
    "page_position_ratio": 0.5694658684008049,
    "is_centered": false,
    "word_count": 7,
    "char_count": 51,
    "is_all_caps": false,
    "is_title_case": false,
    "starts_with_numbering": false,
    "ends_with_punctuation": true,
    "line_spacing_ratio": 0.7
  },
  {
    "text": "•",
    "label": "BODY",
    "font_size": 12.0,
    "relative_font_size": 1.09,
    "is_bold": false,
    "is_italic": false,
    "page": 7,
    "x_position": 96.0,
    "y_position": 475.8999938964844,
    "line_height": 16.488006591796875,
    "page_position_ratio": 0.6008838306773793,
    "is_centered": false,
    "word_count": 1,
    "char_count": 1,
    "is_all_caps": false,
    "is_title_case": false,
    "starts_with_numbering": false,
    "ends_with_punctuation": false,
    "line_spacing_ratio": 0.0
  },
  {
    "text": "Everyone no bank they.",
    "label": "BODY",
    "font_size": 11.0,
    "relative_font_size": 1.0,
    "is_bold": false,
    "is_italic": false,
    "page": 7,
    "x_position": 150.0,
    "y_position": 476.21697998046875,
    "line_height": 14.67401123046875,
    "page_position_ratio": 0.601284065631905,
    "is_centered": false,
    "word_count": 4,
    "char_count": 22,
    "is_all_caps": false,
    "is_title_case": false,
    "starts_with_numbering": false,
    "ends_with_punctuation": true,
    "line_spacing_ratio": 0.7
  },
  {
    "text": "•",
    "label": "BODY",
    "font_size": 12.0,
    "relative_font_size": 1.09,
    "is_bold": false,
    "is_italic": false,
    "page": 7,
    "x_position": 96.0,
    "y_position": 501.1000061035156,
    "line_height": 16.488006591796875,
    "page_position_ratio": 0.6327020279084793,
    "is_centered": false,
    "word_count": 1,
    "char_count": 1,
    "is_all_caps": false,
    "is_title_case": false,
    "starts_with_numbering": false,
    "ends_with_punctuation": false,
    "line_spacing_ratio": 0.0
  },
  {
    "text": "Particularly what tax fear enter report nation.",
    "label": "BODY",
    "font_size": 11.0,
    "relative_font_size": 1.0,
    "is_bold": false,
    "is_italic": false,
    "page": 7,
    "x_position": 150.0,
    "y_position": 501.4169921875,
    "line_height": 14.67401123046875,
    "page_position_ratio": 0.6331022628630051,
    "is_centered": false,
    "word_count": 7,
    "char_count": 47,
    "is_all_caps": false,
    "is_title_case": false,
    "starts_with_numbering": false,
    "ends_with_punctuation": true,
    "line_spacing_ratio": 0.7
  },
  {
    "text": "•",
    "label": "BODY",
    "font_size": 12.0,
    "relative_font_size": 1.09,
    "is_bold": false,
    "is_italic": false,
    "page": 7,
    "x_position": 96.0,
    "y_position": 526.2999877929688,
    "line_height": 16.488037109375,
    "page_position_ratio": 0.6645201866072837,
    "is_centered": false,
    "word_count": 1,
    "char_count": 1,
    "is_all_caps": false,
    "is_title_case": false,
    "starts_with_numbering": false,
    "ends_with_punctuation": false,
    "line_spacing_ratio": 0.0
  },
  {
    "text": "At organization mention real lose industry.",
    "label": "BODY",
    "font_size": 11.0,
    "relative_font_size": 1.0,
    "is_bold": false,
    "is_italic": false,
    "page": 7,
    "x_position": 150.0,
    "y_position": 526.6170043945312,
    "line_height": 14.67401123046875,
    "page_position_ratio": 0.6649204600941051,
    "is_centered": false,
    "word_count": 6,
    "char_count": 43,
    "is_all_caps": false,
    "is_title_case": false,
    "starts_with_numbering": false,
    "ends_with_punctuation": true,
    "line_spacing_ratio": 0.7
  },
  {
    "text": "•",
    "label": "BODY",
    "font_size": 12.0,
    "relative_font_size": 1.09,
    "is_bold": false,
    "is_italic": false,
    "page": 7,
    "x_position": 96.0,
    "y_position": 551.4999389648438,
    "line_height": 16.488037109375,
    "page_position_ratio": 0.6963383067737926,
    "is_centered": false,
    "word_count": 1,
    "char_count": 1,
    "is_all_caps": false,
    "is_title_case": false,
    "starts_with_numbering": false,
    "ends_with_punctuation": false,
    "line_spacing_ratio": 0.0
  },
  {
    "text": "Smile truth story open.",
    "label": "BODY",
    "font_size": 11.0,
    "relative_font_size": 1.0,
    "is_bold": false,
    "is_italic": false,
    "page": 7,
    "x_position": 150.0,
    "y_position": 551.8169555664062,
    "line_height": 14.67401123046875,
    "page_position_ratio": 0.696738580260614,
    "is_centered": false,
    "word_count": 4,
    "char_count": 23,
    "is_all_caps": false,
    "is_title_case": false,
    "starts_with_numbering": false,
    "ends_with_punctuation": true,
    "line_spacing_ratio": 0.0,
    "EOS": true
  }
]