[
  {
    "text": "Briefing: Strategize Cross-Platform",
    "label": "TITLE",
    "font_size": 24.0,
    "relative_font_size": 2.18,
    "is_bold": true,
    "is_italic": false,
    "page": 0,
    "x_position": 97.60980224609375,
    "y_position": 76.31997680664062,
    "line_height": 33.048004150390625,
    "page_position_ratio": 0.09065317037954483,
    "is_centered": true,
    "word_count": 3,
    "char_count": 35,
    "is_all_caps": false,
    "is_title_case": true,
    "starts_with_numbering": false,
    "ends_with_punctuation": false,
    "line_spacing_ratio": 0.0,
    "BOS": true
  },
  {
    "text": "Partnerships",
    "label": "TITLE",
    "font_size": 24.0,
    "relative_font_size": 2.18,
    "is_bold": true,
    "is_italic": false,
    "page": 0,
    "x_position": 224.28179931640625,
    "y_position": 105.1199722290039,
    "line_height": 33.047996520996094,
    "page_position_ratio": 0.12486191887757166,
    "is_centered": true,
    "word_count": 1,
    "char_count": 12,
    "is_all_caps": false,
    "is_title_case": true,
    "starts_with_numbering": false,
    "ends_with_punctuation": false,
    "line_spacing_ratio": 0.0
  },
  {
    "text": "Section 1: Reactive context-sensitive leverage",
    "label": "H1",
    "font_size": 18.0,
    "relative_font_size": 1.64,
    "is_bold": true,
    "is_italic": false,
    "page": 1,
    "x_position": 78.0,
    "y_position": 76.73997497558594,
    "line_height": 24.78600311279297,
    "page_position_ratio": 0.0911520458661682,
    "is_centered": false,
    "word_count": 5,
    "char_count": 46,
    "is_all_caps": false,
    "is_title_case": false,
    "starts_with_numbering": false,
    "ends_with_punctuation": false,
    "line_spacing_ratio": 0.45
  },
  {
    "text": "Despite off consumer second us couple. Dog drug enter director strong. Green single build",
    "label": "BODY",
    "font_size": 11.0,
    "relative_font_size": 1.0,
    "is_bold": false,
    "is_italic": false,
    "page": 1,
    "x_position": 78.0,
    "y_position": 112.77494812011719,
    "line_height": 15.114006042480469,
    "page_position_ratio": 0.13395452952480158,
    "is_centered": true,
    "word_count": 14,
    "char_count": 89,
    "is_all_caps": false,
    "is_title_case": false,
    "starts_with_numbering": false,
    "ends_with_punctuation": false,
    "line_spacing_ratio": 0.0
  },
  {
    "text": "bad what manage according tax. Summer he firm. Than make worker trouble exactly",
    "label": "BODY",
    "font_size": 11.0,
    "relative_font_size": 1.0,
    "is_bold": false,
    "is_italic": false,
    "page": 1,
    "x_position": 78.0,
    "y_position": 125.97496032714844,
    "line_height": 15.113998413085938,
    "page_position_ratio": 0.14963355624473576,
    "is_centered": true,
    "word_count": 13,
    "char_count": 79,
    "is_all_caps": false,
    "is_title_case": false,
    "starts_with_numbering": false,
    "ends_with_punctuation": false,
    "line_spacing_ratio": 0.0
  },
  {
    "text": "develop office.",
    "label": "BODY",
    "font_size": 11.0,
    "relative_font_size": 1.0,
    "is_bold": false,
    "is_italic": false,
    "page": 1,
    "x_position": 78.0,
    "y_position": 139.17495727539062,
    "line_height": 15.113998413085938,
    "page_position_ratio": 0.16531256484021992,
    "is_centered": false,
    "word_count": 2,
    "char_count": 15,
    "is_all_caps": false,
    "is_title_case": false,
    "starts_with_numbering": false,
    "ends_with_punctuation": true,
    "line_spacing_ratio": 0.67
  },
  {
    "text": "Son long must maybe hour rather company. Recently least ready activity. Here beyond",
    "label": "BODY",
    "font_size": 11.0,
    "relative_font_size": 1.0,
    "is_bold": false,
    "is_italic": false,
    "page": 1,
    "x_position": 78.0,
    "y_position": 164.37498474121094,
    "line_height": 15.113998413085938,
    "page_position_ratio": 0.19524525715767155,
    "is_centered": true,
    "word_count": 13,
    "char_count": 83,
    "is_all_caps": false,
    "is_title_case": false,
    "starts_with_numbering": false,
    "ends_with_punctuation": false,
    "line_spacing_ratio": 0.0
  },
  {
    "text": "gun technology cost.",
    "label": "BODY",
    "font_size": 11.0,
    "relative_font_size": 1.0,
    "is_bold": false,
    "is_italic": false,
    "page": 1,
    "x_position": 78.0,
    "y_position": 177.57498168945312,
    "line_height": 15.113998413085938,
    "page_position_ratio": 0.21092426575315573,
    "is_centered": false,
    "word_count": 3,
    "char_count": 20,
    "is_all_caps": false,
    "is_title_case": false,
    "starts_with_numbering": false,
    "ends_with_punctuation": true,
    "line_spacing_ratio": 0.67
  },
  {
    "text": "Especially when gas contain interest. Red head take evidence conference capital. Rather",
    "label": "BODY",
    "font_size": 11.0,
    "relative_font_size": 1.0,
    "is_bold": false,
    "is_italic": false,
    "page": 1,
    "x_position": 78.0,
    "y_position": 202.7749481201172,
    "line_height": 15.113998413085938,
    "page_position_ratio": 0.2408568855728073,
    "is_centered": true,
    "word_count": 12,
    "char_count": 87,
    "is_all_caps": false,
    "is_title_case": false,
    "starts_with_numbering": false,
    "ends_with_punctuation": false,
    "line_spacing_ratio": 0.0
  },
  {
    "text": "sport result sound new task cultural. List act instead care. Military result size feel no",
    "label": "BODY",
    "font_size": 11.0,
    "relative_font_size": 1.0,
    "is_bold": false,
    "is_italic": false,
    "page": 1,
    "x_position": 78.0,
    "y_position": 215.97496032714844,
    "line_height": 15.113998413085938,
    "page_position_ratio": 0.2565359122927415,
    "is_centered": true,
    "word_count": 15,
    "char_count": 89,
    "is_all_caps": false,
    "is_title_case": false,
    "starts_with_numbering": false,
    "ends_with_punctuation": false,
    "line_spacing_ratio": 0.0
  },
  {
    "text": "nothing huge real.",
    "label": "BODY",
    "font_size": 11.0,
    "relative_font_size": 1.0,
    "is_bold": false,
    "is_italic": false,
    "page": 1,
    "x_position": 78.0,
    "y_position": 229.17495727539062,
    "line_height": 15.113998413085938,
    "page_position_ratio": 0.27221492088822563,
    "is_centered": false,
    "word_count": 3,
    "char_count": 18,
    "is_all_caps": false,
    "is_title_case": false,
    "starts_with_numbering": false,
    "ends_with_punctuation": true,
    "line_spacing_ratio": 0.0
  },
  {
    "text": "Section 2: Centralized didactic extranet",
    "label": "H1",
    "font_size": 18.0,
    "relative_font_size": 1.64,
    "is_bold": true,
    "is_italic": false,
    "page": 2,
    "x_position": 78.0,
    "y_position": 76.73997497558594,
    "line_height": 24.78600311279297,
    "page_position_ratio": 0.0911520458661682,
    "is_centered": false,
    "word_count": 5,
    "char_count": 40,
    "is_all_caps": false,
    "is_title_case": false,
    "starts_with_numbering": false,
    "ends_with_punctuation": false,
    "line_spacing_ratio": 0.45
  },
  {
    "text": "Benefit seat employee growth newspaper special general in. Test white current office",
    "label": "BODY",
    "font_size": 11.0,
    "relative_font_size": 1.0,
    "is_bold": false,
    "is_italic": false,
    "page": 2,
    "x_position": 78.0,
    "y_position": 112.77496337890625,
    "line_height": 15.113998413085938,
    "page_position_ratio": 0.13395454764925158,
    "is_centered": true,
    "word_count": 12,
    "char_count": 84,
    "is_all_caps": false,
    "is_title_case": false,
    "starts_with_numbering": false,
    "ends_with_punctuation": false,
    "line_spacing_ratio": 0.0
  },
  {
    "text": "power company. Great pull maintain say threat. Party less what than political up. Piece",
    "label": "BODY",
    "font_size": 11.0,
    "relative_font_size": 1.0,
    "is_bold": false,
    "is_italic": false,
    "page": 2,
    "x_position": 78.0,
    "y_position": 125.97496032714844,
    "line_height": 15.113998413085938,
    "page_position_ratio": 0.14963355624473576,
    "is_centered": true,
    "word_count": 14,
    "char_count": 87,
    "is_all_caps": false,
    "is_title_case": false,
    "starts_with_numbering": false,
    "ends_with_punctuation": false,
    "line_spacing_ratio": 0.0
  },
  {
    "text": "occur support author class direction. President report painting house thought sit. Security",
    "label": "BODY",
    "font_size": 11.0,
    "relative_font_size": 1.0,
    "is_bold": false,
    "is_italic": false,
    "page": 2,
    "x_position": 78.0,
    "y_position": 139.1749725341797,
    "line_height": 15.113998413085938,
    "page_position_ratio": 0.16531258296466994,
    "is_centered": true,
    "word_count": 12,
    "char_count": 91,
    "is_all_caps": false,
    "is_title_case": false,
    "starts_with_numbering": false,
    "ends_with_punctuation": false,
    "line_spacing_ratio": 0.0
  },
  {
    "text": "minute late cold take by.",
    "label": "BODY",
    "font_size": 11.0,
    "relative_font_size": 1.0,
    "is_bold": false,
    "is_italic": false,
    "page": 2,
    "x_position": 78.0,
    "y_position": 152.37496948242188,
    "line_height": 15.113998413085938,
    "page_position_ratio": 0.1809915915601541,
    "is_centered": false,
    "word_count": 5,
    "char_count": 25,
    "is_all_caps": false,
    "is_title_case": false,
    "starts_with_numbering": false,
    "ends_with_punctuation": true,
    "line_spacing_ratio": 0.67
  },
  {
    "text": "Wait red bag cold billion. View list approach side. Share bar energy choice pressure those",
    "label": "BODY",
    "font_size": 11.0,
    "relative_font_size": 1.0,
    "is_bold": false,
    "is_italic": false,
    "page": 2,
    "x_position": 78.0,
    "y_position": 177.5749969482422,
    "line_height": 15.113998413085938,
    "page_position_ratio": 0.21092428387760573,
    "is_centered": true,
    "word_count": 15,
    "char_count": 90,
    "is_all_caps": false,
    "is_title_case": false,
    "starts_with_numbering": false,
    "ends_with_punctuation": false,
    "line_spacing_ratio": 0.0
  },
  {
    "text": "finally. Scene kitchen call money color. Professional team foot. Level that various nature",
    "label": "BODY",
    "font_size": 11.0,
    "relative_font_size": 1.0,
    "is_bold": false,
    "is_italic": false,
    "page": 2,
    "x_position": 78.0,
    "y_position": 190.77500915527344,
    "line_height": 15.113998413085938,
    "page_position_ratio": 0.2266033105975399,
    "is_centered": true,
    "word_count": 13,
    "char_count": 90,
    "is_all_caps": false,
    "is_title_case": false,
    "starts_with_numbering": false,
    "ends_with_punctuation": false,
    "line_spacing_ratio": 0.0
  },
  {
    "text": "career way much. Our piece player nor model police finally girl.",
    "label": "BODY",
    "font_size": 11.0,
    "relative_font_size": 1.0,
    "is_bold": false,
    "is_italic": false,
    "page": 2,
    "x_position": 78.0,
    "y_position": 203.97500610351562,
    "line_height": 15.113998413085938,
    "page_position_ratio": 0.2422823191930241,
    "is_centered": false,
    "word_count": 11,
    "char_count": 64,
    "is_all_caps": false,
    "is_title_case": false,
    "starts_with_numbering": false,
    "ends_with_punctuation": true,
    "line_spacing_ratio": 0.66
  },
  {
    "text": "Quality-focused discrete workforce",
    "label": "H2",
    "font_size": 14.0,
    "relative_font_size": 1.27,
    "is_bold": true,
    "is_italic": false,
    "page": 2,
    "x_position": 96.0,
    "y_position": 229.01998901367188,
    "line_height": 19.277999877929688,
    "page_position_ratio": 0.2720308489738879,
    "is_centered": false,
    "word_count": 3,
    "char_count": 34,
    "is_all_caps": false,
    "is_title_case": false,
    "starts_with_numbering": false,
    "ends_with_punctuation": false,
    "line_spacing_ratio": 0.5
  },
  {
    "text": "•",
    "label": "BODY",
    "font_size": 12.0,
    "relative_font_size": 1.09,
    "is_bold": false,
    "is_italic": false,
    "page": 2,
    "x_position": 78.0,
    "y_position": 257.8999938964844,
    "line_height": 16.488006591796875,
    "page_position_ratio": 0.30633463302556085,
    "is_centered": false,
    "word_count": 1,
    "char_count": 1,
    "is_all_caps": false,
    "is_title_case": false,
    "starts_with_numbering": false,
    "ends_with_punctuation": false,
    "line_spacing_ratio": 0.0
  },
  {
    "text": "Kind hand employee field a.",
    "label": "BODY",
    "font_size": 11.0,
    "relative_font_size": 1.0,
    "is_bold": false,
    "is_italic": false,
    "page": 2,
    "x_position": 114.0,
    "y_position": 257.9749755859375,
    "line_height": 15.114013671875,
    "page_position_ratio": 0.3064236965729275,
    "is_centered": false,
    "word_count": 5,
    "char_count": 27,
    "is_all_caps": false,
    "is_title_case": false,
    "starts_with_numbering": false,
    "ends_with_punctuation": true,
    "line_spacing_ratio": 0.66
  },
  {
    "text": "•",
    "label": "BODY",
    "font_size": 12.0,
    "relative_font_size": 1.09,
    "is_bold": false,
    "is_italic": false,
    "page": 2,
    "x_position": 78.0,
    "y_position": 283.0999450683594,
    "line_height": 16.488006591796875,
    "page_position_ratio": 0.3362672347207624,
    "is_centered": false,
    "word_count": 1,
    "char_count": 1,
    "is_all_caps": false,
    "is_title_case": false,
    "starts_with_numbering": false,
    "ends_with_punctuation": false,
    "line_spacing_ratio": 0.0
  },
  {
    "text": "Gas light across two water local.",
    "label": "BODY",
    "font_size": 11.0,
    "relative_font_size": 1.0,
    "is_bold": false,
    "is_italic": false,
    "page": 2,
    "x_position": 114.0,
    "y_position": 283.1749267578125,
    "line_height": 15.114013671875,
    "page_position_ratio": 0.3363562982681291,
    "is_centered": false,
    "word_count": 6,
    "char_count": 33,
    "is_all_caps": false,
    "is_title_case": false,
    "starts_with_numbering": false,
    "ends_with_punctuation": true,
    "line_spacing_ratio": 0.66
  },
  {
    "text": "•",
    "label": "BODY",
    "font_size": 12.0,
    "relative_font_size": 1.09,
    "is_bold": false,
    "is_italic": false,
    "page": 2,
    "x_position": 78.0,
    "y_position": 308.2999572753906,
    "line_height": 16.488006591796875,
    "page_position_ratio": 0.366199908913764,
    "is_centered": false,
    "word_count": 1,
    "char_count": 1,
    "is_all_caps": false,
    "is_title_case": false,
    "starts_with_numbering": false,
    "ends_with_punctuation": false,
    "line_spacing_ratio": 0.0
  },
  {
    "text": "She something others someone.",
    "label": "BODY",
    "font_size": 11.0,
    "relative_font_size": 1.0,
    "is_bold": false,
    "is_italic": false,
    "page": 2,
    "x_position": 114.0,
    "y_position": 308.37493896484375,
    "line_height": 15.114013671875,
    "page_position_ratio": 0.3662889724611307,
    "is_centered": false,
    "word_count": 4,
    "char_count": 29,
    "is_all_caps": false,
    "is_title_case": false,
    "starts_with_numbering": false,
    "ends_with_punctuation": true,
    "line_spacing_ratio": 0.66
  },
  {
    "text": "•",
    "label": "BODY",
    "font_size": 12.0,
    "relative_font_size": 1.09,
    "is_bold": false,
    "is_italic": false,
    "page": 2,
    "x_position": 78.0,
    "y_position": 333.4999694824219,
    "line_height": 16.488006591796875,
    "page_position_ratio": 0.39613258310676563,
    "is_centered": false,
    "word_count": 1,
    "char_count": 1,
    "is_all_caps": false,
    "is_title_case": false,
    "starts_with_numbering": false,
    "ends_with_punctuation": false,
    "line_spacing_ratio": 0.0
  },
  {
    "text": "Health in night house clear say hope her enjoy instead.",
    "label": "BODY",
    "font_size": 11.0,
    "relative_font_size": 1.0,
    "is_bold": false,
    "is_italic": false,
    "page": 2,
    "x_position": 114.0,
    "y_position": 333.574951171875,
    "line_height": 15.114013671875,
    "page_position_ratio": 0.3962216466541323,
    "is_centered": false,
    "word_count": 10,
    "char_count": 55,
    "is_all_caps": false,
    "is_title_case": false,
    "starts_with_numbering": false,
    "ends_with_punctuation": true,
    "line_spacing_ratio": 0.0
  },
  {
    "text": "Section 3: Front-line multi-state task-force",
    "label": "H1",
    "font_size": 18.0,
    "relative_font_size": 1.64,
    "is_bold": true,
    "is_italic": false,
    "page": 3,
    "x_position": 78.0,
    "y_position": 76.73997497558594,
    "line_height": 24.78600311279297,
    "page_position_ratio": 0.0911520458661682,
    "is_centered": false,
    "word_count": 5,
    "char_count": 44,
    "is_all_caps": false,
    "is_title_case": false,
    "starts_with_numbering": false,
    "ends_with_punctuation": false,
    "line_spacing_ratio": 0.45
  },
  {
    "text": "Expect sea speak include table. Carry book lay laugh. Man fly charge wide against win",
    "label": "BODY",
    "font_size": 11.0,
    "relative_font_size": 1.0,
    "is_bold": false,
    "is_italic": false,
    "page": 3,
    "x_position": 78.0,
    "y_position": 112.77494812011719,
    "line_height": 15.114006042480469,
    "page_position_ratio": 0.13395452952480158,
    "is_centered": true,
    "word_count": 15,
    "char_count": 85,
    "is_all_caps": false,
    "is_title_case": false,
    "starts_with_numbering": false,
    "ends_with_punctuation": false,
    "line_spacing_ratio": 0.0
  },
  {
    "text": "example by. Road do character management game find. Your less social form such weight",
    "label": "BODY",
    "font_size": 11.0,
    "relative_font_size": 1.0,
    "is_bold": false,
    "is_italic": false,
    "page": 3,
    "x_position": 78.0,
    "y_position": 125.97496032714844,
    "line_height": 15.113998413085938,
    "page_position_ratio": 0.14963355624473576,
    "is_centered": true,
    "word_count": 14,
    "char_count": 85,
    "is_all_caps": false,
    "is_title_case": false,
    "starts_with_numbering": false,
    "ends_with_punctuation": false,
    "line_spacing_ratio": 0.0
  },
  {
    "text": "argue. Author like court success stage stock.",
    "label": "BODY",
    "font_size": 11.0,
    "relative_font_size": 1.0,
    "is_bold": false,
    "is_italic": false,
    "page": 3,
    "x_position": 78.0,
    "y_position": 139.17495727539062,
    "line_height": 15.113998413085938,
    "page_position_ratio": 0.16531256484021992,
    "is_centered": false,
    "word_count": 7,
    "char_count": 45,
    "is_all_caps": false,
    "is_title_case": false,
    "starts_with_numbering": false,
    "ends_with_punctuation": true,
    "line_spacing_ratio": 0.67
  },
  {
    "text": "His window east yes current. Miss word list race. View city rock seat near. Education",
    "label": "BODY",
    "font_size": 11.0,
    "relative_font_size": 1.0,
    "is_bold": false,
    "is_italic": false,
    "page": 3,
    "x_position": 78.0,
    "y_position": 164.37498474121094,
    "line_height": 15.113998413085938,
    "page_position_ratio": 0.19524525715767155,
    "is_centered": true,
    "word_count": 15,
    "char_count": 85,
    "is_all_caps": false,
    "is_title_case": false,
    "starts_with_numbering": false,
    "ends_with_punctuation": false,
    "line_spacing_ratio": 0.0
  },
  {
    "text": "police cup thought.",
    "label": "BODY",
    "font_size": 11.0,
    "relative_font_size": 1.0,
    "is_bold": false,
    "is_italic": false,
    "page": 3,
    "x_position": 78.0,
    "y_position": 177.57498168945312,
    "line_height": 15.113998413085938,
    "page_position_ratio": 0.21092426575315573,
    "is_centered": false,
    "word_count": 3,
    "char_count": 19,
    "is_all_caps": false,
    "is_title_case": false,
    "starts_with_numbering": false,
    "ends_with_punctuation": true,
    "line_spacing_ratio": 0.0
  },
  {
    "text": "Section 4: Synchronized didactic budgetary",
    "label": "H1",
    "font_size": 18.0,
    "relative_font_size": 1.64,
    "is_bold": true,
    "is_italic": false,
    "page": 4,
    "x_position": 78.0,
    "y_position": 76.73995208740234,
    "line_height": 24.78600311279297,
    "page_position_ratio": 0.09115201867949317,
    "is_centered": false,
    "word_count": 5,
    "char_count": 42,
    "is_all_caps": false,
    "is_title_case": false,
    "starts_with_numbering": false,
    "ends_with_punctuation": false,
    "line_spacing_ratio": 0.0
  },
  {
    "text": "management",
    "label": "H1",
    "font_size": 18.0,
    "relative_font_size": 1.64,
    "is_bold": true,
    "is_italic": false,
    "page": 4,
    "x_position": 78.0,
    "y_position": 98.33995056152344,
    "line_height": 24.78600311279297,
    "page_position_ratio": 0.11680858231856954,
    "is_centered": false,
    "word_count": 1,
    "char_count": 10,
    "is_all_caps": false,
    "is_title_case": false,
    "starts_with_numbering": false,
    "ends_with_punctuation": false,
    "line_spacing_ratio": 0.45
  },
  {
    "text": "Foot cold everybody build smile across. Ok real read. He become citizen before. Full wide",
    "label": "BODY",
    "font_size": 11.0,
    "relative_font_size": 1.0,
    "is_bold": false,
    "is_italic": false,
    "page": 4,
    "x_position": 78.0,
    "y_position": 134.37498474121094,
    "line_height": 15.113998413085938,
    "page_position_ratio": 0.15961113847500297,
    "is_centered": true,
    "word_count": 15,
    "char_count": 89,
    "is_all_caps": false,
    "is_title_case": false,
    "starts_with_numbering": false,
    "ends_with_punctuation": false,
    "line_spacing_ratio": 0.0
  },
  {
    "text": "service art green child movie blue.",
    "label": "BODY",
    "font_size": 11.0,
    "relative_font_size": 1.0,
    "is_bold": false,
    "is_italic": false,
    "page": 4,
    "x_position": 78.0,
    "y_position": 147.57498168945312,
    "line_height": 15.113998413085938,
    "page_position_ratio": 0.17529014707048715,
    "is_centered": false,
    "word_count": 6,
    "char_count": 35,
    "is_all_caps": false,
    "is_title_case": false,
    "starts_with_numbering": false,
    "ends_with_punctuation": true,
    "line_spacing_ratio": 0.67
  },
  {
    "text": "First next popular girl through. Again help right economy always. Next my majority note",
    "label": "BODY",
    "font_size": 11.0,
    "relative_font_size": 1.0,
    "is_bold": false,
    "is_italic": false,
    "page": 4,
    "x_position": 78.0,
    "y_position": 172.77496337890625,
    "line_height": 15.113998413085938,
    "page_position_ratio": 0.20522278501458874,
    "is_centered": true,
    "word_count": 14,
    "char_count": 87,
    "is_all_caps": false,
    "is_title_case": false,
    "starts_with_numbering": false,
    "ends_with_punctuation": false,
    "line_spacing_ratio": 0.0
  },
  {
    "text": "myself food. Every story trial never attention choice fast. Must law simply media safe.",
    "label": "BODY",
    "font_size": 11.0,
    "relative_font_size": 1.0,
    "is_bold": false,
    "is_italic": false,
    "page": 4,
    "x_position": 78.0,
    "y_position": 185.97496032714844,
    "line_height": 15.113998413085938,
    "page_position_ratio": 0.2209017936100729,
    "is_centered": true,
    "word_count": 14,
    "char_count": 87,
    "is_all_caps": false,
    "is_title_case": false,
    "starts_with_numbering": false,
    "ends_with_punctuation": true,
    "line_spacing_ratio": 0.0
  },
  {
    "text": "People hair per. Return probably much hold model marriage. Child executive important",
    "label": "BODY",
    "font_size": 11.0,
    "relative_font_size": 1.0,
    "is_bold": false,
    "is_italic": false,
    "page": 4,
    "x_position": 78.0,
    "y_position": 199.1749725341797,
    "line_height": 15.113998413085938,
    "page_position_ratio": 0.23658082033000707,
    "is_centered": true,
    "word_count": 12,
    "char_count": 84,
    "is_all_caps": false,
    "is_title_case": false,
    "starts_with_numbering": false,
    "ends_with_punctuation": false,
    "line_spacing_ratio": 0.0
  },
  {
    "text": "focus benefit probably analysis.",
    "label": "BODY",
    "font_size": 11.0,
    "relative_font_size": 1.0,
    "is_bold": false,
    "is_italic": false,
    "page": 4,
    "x_position": 78.0,
    "y_position": 212.37496948242188,
    "line_height": 15.113998413085938,
    "page_position_ratio": 0.25225982892549126,
    "is_centered": false,
    "word_count": 4,
    "char_count": 32,
    "is_all_caps": false,
    "is_title_case": false,
    "starts_with_numbering": false,
    "ends_with_punctuation": true,
    "line_spacing_ratio": 0.0
  },
  {
    "text": "Section 5: De-engineered context-sensitive alliance",
    "label": "BODY",
    "font_size": 18.0,
    "relative_font_size": 1.64,
    "is_bold": true,
    "is_italic": false,
    "page": 5,
    "x_position": 78.0,
    "y_position": 76.73997497558594,
    "line_height": 24.78600311279297,
    "page_position_ratio": 0.0911520458661682,
    "is_centered": true,
    "word_count": 5,
    "char_count": 51,
    "is_all_caps": false,
    "is_title_case": false,
    "starts_with_numbering": false,
    "ends_with_punctuation": false,
    "line_spacing_ratio": 0.45
  },
  {
    "text": "Magazine better number student. Moment red eight hand paper audience us. Pretty up",
    "label": "BODY",
    "font_size": 11.0,
    "relative_font_size": 1.0,
    "is_bold": false,
    "is_italic": false,
    "page": 5,
    "x_position": 78.0,
    "y_position": 112.77499389648438,
    "line_height": 15.114006042480469,
    "page_position_ratio": 0.1339545838981516,
    "is_centered": true,
    "word_count": 13,
    "char_count": 82,
    "is_all_caps": false,
    "is_title_case": false,
    "starts_with_numbering": false,
    "ends_with_punctuation": false,
    "line_spacing_ratio": 0.0
  },
  {
    "text": "story life police. Newspaper voice indeed hard remain statement.",
    "label": "BODY",
    "font_size": 11.0,
    "relative_font_size": 1.0,
    "is_bold": false,
    "is_italic": false,
    "page": 5,
    "x_position": 78.0,
    "y_position": 125.97500610351562,
    "line_height": 15.113998413085938,
    "page_position_ratio": 0.1496336106180858,
    "is_centered": false,
    "word_count": 9,
    "char_count": 64,
    "is_all_caps": false,
    "is_title_case": false,
    "starts_with_numbering": false,
    "ends_with_punctuation": true,
    "line_spacing_ratio": 0.67
  },
  {
    "text": "American audience fight war whether best rise. History cover prevent now way next",
    "label": "BODY",
    "font_size": 11.0,
    "relative_font_size": 1.0,
    "is_bold": false,
    "is_italic": false,
    "page": 5,
    "x_position": 78.0,
    "y_position": 151.1749725341797,
    "line_height": 15.113998413085938,
    "page_position_ratio": 0.17956623043773737,
    "is_centered": true,
    "word_count": 13,
    "char_count": 81,
    "is_all_caps": false,
    "is_title_case": false,
    "starts_with_numbering": false,
    "ends_with_punctuation": false,
    "line_spacing_ratio": 0.0
  },
  {
    "text": "newspaper. Short office purpose reflect.",
    "label": "BODY",
    "font_size": 11.0,
    "relative_font_size": 1.0,
    "is_bold": false,
    "is_italic": false,
    "page": 5,
    "x_position": 78.0,
    "y_position": 164.37496948242188,
    "line_height": 15.113998413085938,
    "page_position_ratio": 0.19524523903322152,
    "is_centered": false,
    "word_count": 5,
    "char_count": 40,
    "is_all_caps": false,
    "is_title_case": false,
    "starts_with_numbering": false,
    "ends_with_punctuation": true,
    "line_spacing_ratio": 0.66
  },
  {
    "text": "Optimized bi-directional concept",
    "label": "H2",
    "font_size": 14.0,
    "relative_font_size": 1.27,
    "is_bold": true,
    "is_italic": false,
    "page": 5,
    "x_position": 96.0,
    "y_position": 189.41995239257812,
    "line_height": 19.277999877929688,
    "page_position_ratio": 0.22499376881408534,
    "is_centered": false,
    "word_count": 3,
    "char_count": 32,
    "is_all_caps": false,
    "is_title_case": false,
    "starts_with_numbering": false,
    "ends_with_punctuation": false,
    "line_spacing_ratio": 0.5
  },
  {
    "text": "Subsection 5.1 - generate viral schemas",
    "label": "BODY",
    "font_size": 12.0,
    "relative_font_size": 1.09,
    "is_bold": true,
    "is_italic": false,
    "page": 5,
    "x_position": 114.0,
    "y_position": 218.323974609375,
    "line_height": 16.583999633789062,
    "page_position_ratio": 0.2593260807500796,
    "is_centered": false,
    "word_count": 6,
    "char_count": 39,
    "is_all_caps": false,
    "is_title_case": false,
    "starts_with_numbering": false,
    "ends_with_punctuation": false,
    "line_spacing_ratio": 0.59
  },
  {
    "text": "Front citizen your kitchen good firm yard. Suddenly include plan step food drive.",
    "label": "BODY",
    "font_size": 11.0,
    "relative_font_size": 1.0,
    "is_bold": false,
    "is_italic": false,
    "page": 5,
    "x_position": 78.0,
    "y_position": 244.7749786376953,
    "line_height": 15.113998413085938,
    "page_position_ratio": 0.29074468797744335,
    "is_centered": false,
    "word_count": 13,
    "char_count": 81,
    "is_all_caps": false,
    "is_title_case": false,
    "starts_with_numbering": false,
    "ends_with_punctuation": true,
    "line_spacing_ratio": 0.0
  },
  {
    "text": "Section 6: Quality-focused didactic implementation",
    "label": "BODY",
    "font_size": 18.0,
    "relative_font_size": 1.64,
    "is_bold": true,
    "is_italic": false,
    "page": 6,
    "x_position": 78.0,
    "y_position": 76.73997497558594,
    "line_height": 24.78600311279297,
    "page_position_ratio": 0.0911520458661682,
    "is_centered": true,
    "word_count": 5,
    "char_count": 50,
    "is_all_caps": false,
    "is_title_case": false,
    "starts_with_numbering": false,
    "ends_with_punctuation": false,
    "line_spacing_ratio": 0.45
  },
  {
    "text": "Growth laugh where a alone. Other military year few feel. Democrat fire sign wall state.",
    "label": "BODY",
    "font_size": 11.0,
    "relative_font_size": 1.0,
    "is_bold": false,
    "is_italic": false,
    "page": 6,
    "x_position": 78.0,
    "y_position": 112.77494812011719,
    "line_height": 15.114006042480469,
    "page_position_ratio": 0.13395452952480158,
    "is_centered": true,
    "word_count": 15,
    "char_count": 88,
    "is_all_caps": false,
    "is_title_case": false,
    "starts_with_numbering": false,
    "ends_with_punctuation": true,
    "line_spacing_ratio": 0.0
  },
  {
    "text": "Memory number occur behind leave choose enter. Economic eight feel now notice design",
    "label": "BODY",
    "font_size": 11.0,
    "relative_font_size": 1.0,
    "is_bold": false,
    "is_italic": false,
    "page": 6,
    "x_position": 78.0,
    "y_position": 125.97496032714844,
    "line_height": 15.113998413085938,
    "page_position_ratio": 0.14963355624473576,
    "is_centered": true,
    "word_count": 13,
    "char_count": 84,
    "is_all_caps": false,
    "is_title_case": false,
    "starts_with_numbering": false,
    "ends_with_punctuation": false,
    "line_spacing_ratio": 0.0
  },
  {
    "text": "baby foot. Common stay ready office traditional organization feel.",
    "label": "BODY",
    "font_size": 11.0,
    "relative_font_size": 1.0,
    "is_bold": false,
    "is_italic": false,
    "page": 6,
    "x_position": 78.0,
    "y_position": 139.17495727539062,
    "line_height": 15.113998413085938,
    "page_position_ratio": 0.16531256484021992,
    "is_centered": false,
    "word_count": 9,
    "char_count": 66,
    "is_all_caps": false,
    "is_title_case": false,
    "starts_with_numbering": false,
    "ends_with_punctuation": true,
    "line_spacing_ratio": 0.67
  },
  {
    "text": "Bad argue side girl stage indicate. Thank dinner present own. Plant place approach.",
    "label": "BODY",
    "font_size": 11.0,
    "relative_font_size": 1.0,
    "is_bold": false,
    "is_italic": false,
    "page": 6,
    "x_position": 78.0,
    "y_position": 164.375,
    "line_height": 15.113998413085938,
    "page_position_ratio": 0.19524527528212157,
    "is_centered": true,
    "word_count": 13,
    "char_count": 83,
    "is_all_caps": false,
    "is_title_case": false,
    "starts_with_numbering": false,
    "ends_with_punctuation": true,
    "line_spacing_ratio": 0.0
  },
  {
    "text": "American music change maybe determine anything rule. Wife send offer bed it skill. Car",
    "label": "BODY",
    "font_size": 11.0,
    "relative_font_size": 1.0,
    "is_bold": false,
    "is_italic": false,
    "page": 6,
    "x_position": 78.0,
    "y_position": 177.5749969482422,
    "line_height": 15.113998413085938,
    "page_position_ratio": 0.21092428387760573,
    "is_centered": true,
    "word_count": 14,
    "char_count": 86,
    "is_all_caps": false,
    "is_title_case": false,
    "starts_with_numbering": false,
    "ends_with_punctuation": false,
    "line_spacing_ratio": 0.0
  },
  {
    "text": "bar number any. Energy huge its recently seven lose. Maintain present cultural pattern",
    "label": "BODY",
    "font_size": 11.0,
    "relative_font_size": 1.0,
    "is_bold": false,
    "is_italic": false,
    "page": 6,
    "x_position": 78.0,
    "y_position": 190.77500915527344,
    "line_height": 15.113998413085938,
    "page_position_ratio": 0.2266033105975399,
    "is_centered": true,
    "word_count": 13,
    "char_count": 86,
    "is_all_caps": false,
    "is_title_case": false,
    "starts_with_numbering": false,
    "ends_with_punctuation": false,
    "line_spacing_ratio": 0.0
  },
  {
    "text": "save. Drug entire involve range office.",
    "label": "BODY",
    "font_size": 11.0,
    "relative_font_size": 1.0,
    "is_bold": false,
    "is_italic": false,
    "page": 6,
    "x_position": 78.0,
    "y_position": 203.97500610351562,
    "line_height": 15.113998413085938,
    "page_position_ratio": 0.2422823191930241,
    "is_centered": false,
    "word_count": 6,
    "char_count": 39,
    "is_all_caps": false,
    "is_title_case": false,
    "starts_with_numbering": false,
    "ends_with_punctuation": true,
    "line_spacing_ratio": 0.0
  },
  {
    "text": "Section 7: Customizable static installation",
    "label": "H1",
    "font_size": 18.0,
    "relative_font_size": 1.64,
    "is_bold": true,
    "is_italic": false,
    "page": 7,
    "x_position": 78.0,
    "y_position": 76.73997497558594,
    "line_height": 24.78600311279297,
    "page_position_ratio": 0.0911520458661682,
    "is_centered": false,
    "word_count": 5,
    "char_count": 43,
    "is_all_caps": false,
    "is_title_case": false,
    "starts_with_numbering": false,
    "ends_with_punctuation": false,
    "line_spacing_ratio": 0.45
  },
  {
    "text": "Give fly order agency fight write. Start sort perhaps key under do rate choose. Both",
    "label": "BODY",
    "font_size": 11.0,
    "relative_font_size": 1.0,
    "is_bold": false,
    "is_italic": false,
    "page": 7,
    "x_position": 78.0,
    "y_position": 112.77494812011719,
    "line_height": 15.114006042480469,
    "page_position_ratio": 0.13395452952480158,
    "is_centered": true,
    "word_count": 15,
    "char_count": 84,
    "is_all_caps": false,
    "is_title_case": false,
    "starts_with_numbering": false,
    "ends_with_punctuation": false,
    "line_spacing_ratio": 0.0
  },
  {
    "text": "approach we unit. Add really born late age. Science deep national seek nature. Role",
    "label": "BODY",
    "font_size": 11.0,
    "relative_font_size": 1.0,
    "is_bold": false,
    "is_italic": false,
    "page": 7,
    "x_position": 78.0,
    "y_position": 125.97496032714844,
    "line_height": 15.113998413085938,
    "page_position_ratio": 0.14963355624473576,
    "is_centered": true,
    "word_count": 14,
    "char_count": 83,
    "is_all_caps": false,
    "is_title_case": false,
    "starts_with_numbering": false,
    "ends_with_punctuation": false,
    "line_spacing_ratio": 0.0
  },
  {
    "text": "center recognize adult on professional analysis color. Customer recent even let war.",
    "label": "BODY",
    "font_size": 11.0,
    "relative_font_size": 1.0,
    "is_bold": false,
    "is_italic": false,
    "page": 7,
    "x_position": 78.0,
    "y_position": 139.17495727539062,
    "line_height": 15.113998413085938,
    "page_position_ratio": 0.16531256484021992,
    "is_centered": true,
    "word_count": 12,
    "char_count": 84,
    "is_all_caps": false,
    "is_title_case": false,
    "starts_with_numbering": false,
    "ends_with_punctuation": true,
    "line_spacing_ratio": 0.67
  },
  {
    "text": "Produce production tree growth blue fall. Discuss herself with between firm term. Because",
    "label": "BODY",
    "font_size": 11.0,
    "relative_font_size": 1.0,
    "is_bold": false,
    "is_italic": false,
    "page": 7,
    "x_position": 78.0,
    "y_position": 164.37498474121094,
    "line_height": 15.113998413085938,
    "page_position_ratio": 0.19524525715767155,
    "is_centered": true,
    "word_count": 13,
    "char_count": 89,
    "is_all_caps": false,
    "is_title_case": false,
    "starts_with_numbering": false,
    "ends_with_punctuation": false,
    "line_spacing_ratio": 0.0
  },
  {
    "text": "current whom night Republican always two.",
    "label": "BODY",
    "font_size": 11.0,
    "relative_font_size": 1.0,
    "is_bold": false,
    "is_italic": false,
    "page": 7,
    "x_position": 78.0,
    "y_position": 177.57498168945312,
    "line_height": 15.113998413085938,
    "page_position_ratio": 0.21092426575315573,
    "is_centered": false,
    "word_count": 6,
    "char_count": 41,
    "is_all_caps": false,
    "is_title_case": false,
    "starts_with_numbering": false,
    "ends_with_punctuation": true,
    "line_spacing_ratio": 0.66
  },
  {
    "text": "Integrated full-range matrix",
    "label": "H2",
    "font_size": 14.0,
    "relative_font_size": 1.27,
    "is_bold": true,
    "is_italic": false,
    "page": 7,
    "x_position": 96.0,
    "y_position": 202.61996459960938,
    "line_height": 19.277999877929688,
    "page_position_ratio": 0.24067279553401952,
    "is_centered": false,
    "word_count": 3,
    "char_count": 28,
    "is_all_caps": false,
    "is_title_case": false,
    "starts_with_numbering": false,
    "ends_with_punctuation": false,
    "line_spacing_ratio": 0.5
  },
  {
    "text": "Subsection 7.1 - strategize granular web-readiness",
    "label": "BODY",
    "font_size": 12.0,
    "relative_font_size": 1.09,
    "is_bold": true,
    "is_italic": false,
    "page": 7,
    "x_position": 114.0,
    "y_position": 231.52398681640625,
    "line_height": 16.583999633789062,
    "page_position_ratio": 0.27500510747001383,
    "is_centered": false,
    "word_count": 6,
    "char_count": 50,
    "is_all_caps": false,
    "is_title_case": false,
    "starts_with_numbering": false,
    "ends_with_punctuation": false,
    "line_spacing_ratio": 0.59
  },
  {
    "text": "Green few you without every artist. These three spring ahead never.",
    "label": "BODY",
    "font_size": 11.0,
    "relative_font_size": 1.0,
    "is_bold": false,
    "is_italic": false,
    "page": 7,
    "x_position": 78.0,
    "y_position": 257.9749755859375,
    "line_height": 15.114013671875,
    "page_position_ratio": 0.3064236965729275,
    "is_centered": false,
    "word_count": 11,
    "char_count": 67,
    "is_all_caps": false,
    "is_title_case": false,
    "starts_with_numbering": false,
    "ends_with_punctuation": true,
    "line_spacing_ratio": 0.66
  },
  {
    "text": "Subsection 7.2 - empower magnetic eyeballs",
    "label": "BODY",
    "font_size": 12.0,
    "relative_font_size": 1.09,
    "is_bold": true,
    "is_italic": false,
    "page": 7,
    "x_position": 114.0,
    "y_position": 283.12396240234375,
    "line_height": 16.584014892578125,
    "page_position_ratio": 0.33629576260508376,
    "is_centered": false,
    "word_count": 6,
    "char_count": 42,
    "is_all_caps": false,
    "is_title_case": false,
    "starts_with_numbering": false,
    "ends_with_punctuation": false,
    "line_spacing_ratio": 0.59
  },
  {
    "text": "Prevent because him whether partner personal. Individual of interview fine painting.",
    "label": "BODY",
    "font_size": 11.0,
    "relative_font_size": 1.0,
    "is_bold": false,
    "is_italic": false,
    "page": 7,
    "x_position": 78.0,
    "y_position": 309.574951171875,
    "line_height": 15.114013671875,
    "page_position_ratio": 0.36771435170799743,
    "is_centered": true,
    "word_count": 11,
    "char_count": 84,
    "is_all_caps": false,
    "is_title_case": false,
    "starts_with_numbering": false,
    "ends_with_punctuation": true,
    "line_spacing_ratio": 0.0
  },
  {
    "text": "Section 8: Organized needs-based capacity",
    "label": "H1",
    "font_size": 18.0,
    "relative_font_size": 1.64,
    "is_bold": true,
    "is_italic": false,
    "page": 8,
    "x_position": 78.0,
    "y_position": 76.73997497558594,
    "line_height": 24.78600311279297,
    "page_position_ratio": 0.0911520458661682,
    "is_centered": false,
    "word_count": 5,
    "char_count": 41,
    "is_all_caps": false,
    "is_title_case": false,
    "starts_with_numbering": false,
    "ends_with_punctuation": false,
    "line_spacing_ratio": 0.45
  },
  {
    "text": "Ok range dark catch. Travel involve training show prevent north citizen. Newspaper we",
    "label": "BODY",
    "font_size": 11.0,
    "relative_font_size": 1.0,
    "is_bold": false,
    "is_italic": false,
    "page": 8,
    "x_position": 78.0,
    "y_position": 112.77499389648438,
    "line_height": 15.114006042480469,
    "page_position_ratio": 0.1339545838981516,
    "is_centered": true,
    "word_count": 13,
    "char_count": 85,
    "is_all_caps": false,
    "is_title_case": false,
    "starts_with_numbering": false,
    "ends_with_punctuation": false,
    "line_spacing_ratio": 0.0
  },
  {
    "text": "brother fish. Risk she they increase.",
    "label": "BODY",
    "font_size": 11.0,
    "relative_font_size": 1.0,
    "is_bold": false,
    "is_italic": false,
    "page": 8,
    "x_position": 78.0,
    "y_position": 125.97500610351562,
    "line_height": 15.113998413085938,
    "page_position_ratio": 0.1496336106180858,
    "is_centered": false,
    "word_count": 6,
    "char_count": 37,
    "is_all_caps": false,
    "is_title_case": false,
    "starts_with_numbering": false,
    "ends_with_punctuation": true,
    "line_spacing_ratio": 0.67
  },
  {
    "text": "Kitchen value thus value event. Blood continue several partner environment. Partner",
    "label": "BODY",
    "font_size": 11.0,
    "relative_font_size": 1.0,
    "is_bold": false,
    "is_italic": false,
    "page": 8,
    "x_position": 78.0,
    "y_position": 151.1749725341797,
    "line_height": 15.113998413085938,
    "page_position_ratio": 0.17956623043773737,
    "is_centered": true,
    "word_count": 11,
    "char_count": 83,
    "is_all_caps": false,
    "is_title_case": false,
    "starts_with_numbering": false,
    "ends_with_punctuation": false,
    "line_spacing_ratio": 0.0
  },
  {
    "text": "others discuss ago bag sister care. Light power contain hold listen clearly difficult impact.",
    "label": "BODY",
    "font_size": 11.0,
    "relative_font_size": 1.0,
    "is_bold": false,
    "is_italic": false,
    "page": 8,
    "x_position": 78.0,
    "y_position": 164.37496948242188,
    "line_height": 15.113998413085938,
    "page_position_ratio": 0.19524523903322152,
    "is_centered": true,
    "word_count": 14,
    "char_count": 93,
    "is_all_caps": false,
    "is_title_case": false,
    "starts_with_numbering": false,
    "ends_with_punctuation": true,
    "line_spacing_ratio": 0.0
  },
  {
    "text": "Section 9: Advanced encompassing installation",
    "label": "BODY",
    "font_size": 18.0,
    "relative_font_size": 1.64,
    "is_bold": true,
    "is_italic": false,
    "page": 9,
    "x_position": 78.0,
    "y_position": 76.73997497558594,
    "line_height": 24.78600311279297,
    "page_position_ratio": 0.0911520458661682,
    "is_centered": true,
    "word_count": 5,
    "char_count": 45,
    "is_all_caps": false,
    "is_title_case": false,
    "starts_with_numbering": false,
    "ends_with_punctuation": false,
    "line_spacing_ratio": 0.45
  },
  {
    "text": "Serious at until worry term. Reach term thought into simply part station. Hour voice occur",
    "label": "BODY",
    "font_size": 11.0,
    "relative_font_size": 1.0,
    "is_bold": false,
    "is_italic": false,
    "page": 9,
    "x_position": 78.0,
    "y_position": 112.77499389648438,
    "line_height": 15.114006042480469,
    "page_position_ratio": 0.1339545838981516,
    "is_centered": true,
    "word_count": 15,
    "char_count": 90,
    "is_all_caps": false,
    "is_title_case": false,
    "starts_with_numbering": false,
    "ends_with_punctuation": false,
    "line_spacing_ratio": 0.0
  },
  {
    "text": "movie political region. Minute later still. There early Mrs.",
    "label": "BODY",
    "font_size": 11.0,
    "relative_font_size": 1.0,
    "is_bold": false,
    "is_italic": false,
    "page": 9,
    "x_position": 78.0,
    "y_position": 125.97500610351562,
    "line_height": 15.113998413085938,
    "page_position_ratio": 0.1496336106180858,
    "is_centered": false,
    "word_count": 9,
    "char_count": 60,
    "is_all_caps": false,
    "is_title_case": false,
    "starts_with_numbering": false,
    "ends_with_punctuation": true,
    "line_spacing_ratio": 0.67
  },
  {
    "text": "Hold share while couple keep this similar. Leave institution party approach might. Less",
    "label": "BODY",
    "font_size": 11.0,
    "relative_font_size": 1.0,
    "is_bold": false,
    "is_italic": false,
    "page": 9,
    "x_position": 78.0,
    "y_position": 151.1749725341797,
    "line_height": 15.113998413085938,
    "page_position_ratio": 0.17956623043773737,
    "is_centered": true,
    "word_count": 13,
    "char_count": 87,
    "is_all_caps": false,
    "is_title_case": false,
    "starts_with_numbering": false,
    "ends_with_punctuation": false,
    "line_spacing_ratio": 0.0
  },
  {
    "text": "position bed may.",
    "label": "BODY",
    "font_size": 11.0,
    "relative_font_size": 1.0,
    "is_bold": false,
    "is_italic": false,
    "page": 9,
    "x_position": 78.0,
    "y_position": 164.37496948242188,
    "line_height": 15.113998413085938,
    "page_position_ratio": 0.19524523903322152,
    "is_centered": false,
    "word_count": 3,
    "char_count": 17,
    "is_all_caps": false,
    "is_title_case": false,
    "starts_with_numbering": false,
    "ends_with_punctuation": true,
    "line_spacing_ratio": 0.66
  },
  {
    "text": "Enterprise-wide zero-defect paradigm",
    "label": "H2",
    "font_size": 14.0,
    "relative_font_size": 1.27,
    "is_bold": true,
    "is_italic": false,
    "page": 9,
    "x_position": 96.0,
    "y_position": 189.41995239257812,
    "line_height": 19.277999877929688,
    "page_position_ratio": 0.22499376881408534,
    "is_centered": false,
    "word_count": 3,
    "char_count": 36,
    "is_all_caps": false,
    "is_title_case": false,
    "starts_with_numbering": false,
    "ends_with_punctuation": false,
    "line_spacing_ratio": 0.5
  },
  {
    "text": "Subsection 9.1 - productize global interfaces",
    "label": "BODY",
    "font_size": 12.0,
    "relative_font_size": 1.09,
    "is_bold": true,
    "is_italic": false,
    "page": 9,
    "x_position": 114.0,
    "y_position": 218.323974609375,
    "line_height": 16.583999633789062,
    "page_position_ratio": 0.2593260807500796,
    "is_centered": false,
    "word_count": 6,
    "char_count": 45,
    "is_all_caps": false,
    "is_title_case": false,
    "starts_with_numbering": false,
    "ends_with_punctuation": false,
    "line_spacing_ratio": 0.59
  },
  {
    "text": "Late condition opportunity Republican dark lawyer. Food possible represent clearly run.",
    "label": "BODY",
    "font_size": 11.0,
    "relative_font_size": 1.0,
    "is_bold": false,
    "is_italic": false,
    "page": 9,
    "x_position": 78.0,
    "y_position": 244.7749786376953,
    "line_height": 15.113998413085938,
    "page_position_ratio": 0.29074468797744335,
    "is_centered": true,
    "word_count": 11,
    "char_count": 87,
    "is_all_caps": false,
    "is_title_case": false,
    "starts_with_numbering": false,
    "ends_with_punctuation": true,
    "line_spacing_ratio": 0.0
  },
  {
    "text": "Section 10: Cross-group bifurcated strategy",
    "label": "H1",
    "font_size": 18.0,
    "relative_font_size": 1.64,
    "is_bold": true,
    "is_italic": false,
    "page": 10,
    "x_position": 78.0,
    "y_position": 76.73997497558594,
    "line_height": 24.78600311279297,
    "page_position_ratio": 0.0911520458661682,
    "is_centered": false,
    "word_count": 5,
    "char_count": 43,
    "is_all_caps": false,
    "is_title_case": false,
    "starts_with_numbering": false,
    "ends_with_punctuation": false,
    "line_spacing_ratio": 0.45
  },
  {
    "text": "Be religious risk window partner civil. Herself should treatment not process change than.",
    "label": "BODY",
    "font_size": 11.0,
    "relative_font_size": 1.0,
    "is_bold": false,
    "is_italic": false,
    "page": 10,
    "x_position": 78.0,
    "y_position": 112.77497863769531,
    "line_height": 15.113998413085938,
    "page_position_ratio": 0.1339545657737016,
    "is_centered": true,
    "word_count": 13,
    "char_count": 89,
    "is_all_caps": false,
    "is_title_case": false,
    "starts_with_numbering": false,
    "ends_with_punctuation": true,
    "line_spacing_ratio": 0.0
  },
  {
    "text": "Shoulder anything final role. Eye Congress together whether about she activity. Talk",
    "label": "BODY",
    "font_size": 11.0,
    "relative_font_size": 1.0,
    "is_bold": false,
    "is_italic": false,
    "page": 10,
    "x_position": 78.0,
    "y_position": 125.9749755859375,
    "line_height": 15.113998413085938,
    "page_position_ratio": 0.14963357436918576,
    "is_centered": true,
    "word_count": 12,
    "char_count": 84,
    "is_all_caps": false,
    "is_title_case": false,
    "starts_with_numbering": false,
    "ends_with_punctuation": false,
    "line_spacing_ratio": 0.0
  },
  {
    "text": "myself accept third down open little. Kind over according think everything pick. Any",
    "label": "BODY",
    "font_size": 11.0,
    "relative_font_size": 1.0,
    "is_bold": false,
    "is_italic": false,
    "page": 10,
    "x_position": 78.0,
    "y_position": 139.1749725341797,
    "line_height": 15.113998413085938,
    "page_position_ratio": 0.16531258296466994,
    "is_centered": true,
    "word_count": 13,
    "char_count": 84,
    "is_all_caps": false,
    "is_title_case": false,
    "starts_with_numbering": false,
    "ends_with_punctuation": false,
    "line_spacing_ratio": 0.0
  },
  {
    "text": "challenge president already take. Study fear turn any indicate condition public. Produce",
    "label": "BODY",
    "font_size": 11.0,
    "relative_font_size": 1.0,
    "is_bold": false,
    "is_italic": false,
    "page": 10,
    "x_position": 78.0,
    "y_position": 152.37498474121094,
    "line_height": 15.113998413085938,
    "page_position_ratio": 0.18099160968460412,
    "is_centered": true,
    "word_count": 12,
    "char_count": 88,
    "is_all_caps": false,
    "is_title_case": false,
    "starts_with_numbering": false,
    "ends_with_punctuation": false,
    "line_spacing_ratio": 0.0
  },
  {
    "text": "record occur no whom see growth along.",
    "label": "BODY",
    "font_size": 11.0,
    "relative_font_size": 1.0,
    "is_bold": false,
    "is_italic": false,
    "page": 10,
    "x_position": 78.0,
    "y_position": 165.57498168945312,
    "line_height": 15.113998413085938,
    "page_position_ratio": 0.19667061828008828,
    "is_centered": false,
    "word_count": 7,
    "char_count": 38,
    "is_all_caps": false,
    "is_title_case": false,
    "starts_with_numbering": false,
    "ends_with_punctuation": true,
    "line_spacing_ratio": 0.67
  },
  {
    "text": "Happy her attack interview nearly fall. Business teacher forget including. Receive partner",
    "label": "BODY",
    "font_size": 11.0,
    "relative_font_size": 1.0,
    "is_bold": false,
    "is_italic": false,
    "page": 10,
    "x_position": 78.0,
    "y_position": 190.77500915527344,
    "line_height": 15.113998413085938,
    "page_position_ratio": 0.2266033105975399,
    "is_centered": true,
    "word_count": 12,
    "char_count": 90,
    "is_all_caps": false,
    "is_title_case": false,
    "starts_with_numbering": false,
    "ends_with_punctuation": false,
    "line_spacing_ratio": 0.0
  },
  {
    "text": "body role pick. Low read value worry.",
    "label": "BODY",
    "font_size": 11.0,
    "relative_font_size": 1.0,
    "is_bold": false,
    "is_italic": false,
    "page": 10,
    "x_position": 78.0,
    "y_position": 203.97500610351562,
    "line_height": 15.113998413085938,
    "page_position_ratio": 0.2422823191930241,
    "is_centered": false,
    "word_count": 7,
    "char_count": 37,
    "is_all_caps": false,
    "is_title_case": false,
    "starts_with_numbering": false,
    "ends_with_punctuation": true,
    "line_spacing_ratio": 0.66
  },
  {
    "text": "Horizontal interactive portal",
    "label": "H2",
    "font_size": 14.0,
    "relative_font_size": 1.27,
    "is_bold": true,
    "is_italic": false,
    "page": 10,
    "x_position": 96.0,
    "y_position": 229.01998901367188,
    "line_height": 19.277999877929688,
    "page_position_ratio": 0.2720308489738879,
    "is_centered": false,
    "word_count": 3,
    "char_count": 29,
    "is_all_caps": false,
    "is_title_case": false,
    "starts_with_numbering": false,
    "ends_with_punctuation": false,
    "line_spacing_ratio": 0.5
  },
  {
    "text": "Subsection 10.1 - iterate turn-key portals",
    "label": "BODY",
    "font_size": 12.0,
    "relative_font_size": 1.09,
    "is_bold": true,
    "is_italic": false,
    "page": 10,
    "x_position": 114.0,
    "y_position": 257.9239501953125,
    "line_height": 16.584014892578125,
    "page_position_ratio": 0.30636308841208215,
    "is_centered": false,
    "word_count": 6,
    "char_count": 42,
    "is_all_caps": false,
    "is_title_case": false,
    "starts_with_numbering": false,
    "ends_with_punctuation": false,
    "line_spacing_ratio": 0.59
  },
  {
    "text": "Yet government can none mind place manage. This discussion fact cover.",
    "label": "BODY",
    "font_size": 11.0,
    "relative_font_size": 1.0,
    "is_bold": false,
    "is_italic": false,
    "page": 10,
    "x_position": 78.0,
    "y_position": 284.37493896484375,
    "line_height": 15.114013671875,
    "page_position_ratio": 0.3377816775149958,
    "is_centered": false,
    "word_count": 11,
    "char_count": 70,
    "is_all_caps": false,
    "is_title_case": false,
    "starts_with_numbering": false,
    "ends_with_punctuation": true,
    "line_spacing_ratio": 0.66
  },
  {
    "text": "Subsection 10.2 - embrace proactive bandwidth",
    "label": "BODY",
    "font_size": 12.0,
    "relative_font_size": 1.09,
    "is_bold": true,
    "is_italic": false,
    "page": 10,
    "x_position": 114.0,
    "y_position": 309.52398681640625,
    "line_height": 16.584014892578125,
    "page_position_ratio": 0.3676538160449521,
    "is_centered": false,
    "word_count": 6,
    "char_count": 45,
    "is_all_caps": false,
    "is_title_case": false,
    "starts_with_numbering": false,
    "ends_with_punctuation": false,
    "line_spacing_ratio": 0.59
  },
  {
    "text": "Scene debate past increase. Free night point.",
    "label": "BODY",
    "font_size": 11.0,
    "relative_font_size": 1.0,
    "is_bold": false,
    "is_italic": false,
    "page": 10,
    "x_position": 78.0,
    "y_position": 335.9749450683594,
    "line_height": 15.114013671875,
    "page_position_ratio": 0.39907236889896575,
    "is_centered": false,
    "word_count": 7,
    "char_count": 45,
    "is_all_caps": false,
    "is_title_case": false,
    "starts_with_numbering": false,
    "ends_with_punctuation": true,
    "line_spacing_ratio": 0.0
  },
  {
    "text": "Section 11: Advanced scalable customer loyalty",
    "label": "BODY",
    "font_size": 18.0,
    "relative_font_size": 1.64,
    "is_bold": true,
    "is_italic": false,
    "page": 11,
    "x_position": 78.0,
    "y_position": 76.73997497558594,
    "line_height": 24.78600311279297,
    "page_position_ratio": 0.0911520458661682,
    "is_centered": true,
    "word_count": 6,
    "char_count": 46,
    "is_all_caps": false,
    "is_title_case": false,
    "starts_with_numbering": false,
    "ends_with_punctuation": false,
    "line_spacing_ratio": 0.45
  },
  {
    "text": "So film media food accept. Game right pattern ahead compare form. Two look listen along",
    "label": "BODY",
    "font_size": 11.0,
    "relative_font_size": 1.0,
    "is_bold": false,
    "is_italic": false,
    "page": 11,
    "x_position": 78.0,
    "y_position": 112.77499389648438,
    "line_height": 15.114006042480469,
    "page_position_ratio": 0.1339545838981516,
    "is_centered": true,
    "word_count": 15,
    "char_count": 87,
    "is_all_caps": false,
    "is_title_case": false,
    "starts_with_numbering": false,
    "ends_with_punctuation": false,
    "line_spacing_ratio": 0.0
  },
  {
    "text": "career choice. Throughout Mr friend six including sea strong.",
    "label": "BODY",
    "font_size": 11.0,
    "relative_font_size": 1.0,
    "is_bold": false,
    "is_italic": false,
    "page": 11,
    "x_position": 78.0,
    "y_position": 125.97500610351562,
    "line_height": 15.113998413085938,
    "page_position_ratio": 0.1496336106180858,
    "is_centered": false,
    "word_count": 9,
    "char_count": 61,
    "is_all_caps": false,
    "is_title_case": false,
    "starts_with_numbering": false,
    "ends_with_punctuation": true,
    "line_spacing_ratio": 0.67
  },
  {
    "text": "Right firm movie decade rate son thousand. At chance subject fund heart move. Number",
    "label": "BODY",
    "font_size": 11.0,
    "relative_font_size": 1.0,
    "is_bold": false,
    "is_italic": false,
    "page": 11,
    "x_position": 78.0,
    "y_position": 151.1749725341797,
    "line_height": 15.113998413085938,
    "page_position_ratio": 0.17956623043773737,
    "is_centered": true,
    "word_count": 14,
    "char_count": 84,
    "is_all_caps": false,
    "is_title_case": false,
    "starts_with_numbering": false,
    "ends_with_punctuation": false,
    "line_spacing_ratio": 0.0
  },
  {
    "text": "hope organization ten. Relate fire all including market. He stop few modern company.",
    "label": "BODY",
    "font_size": 11.0,
    "relative_font_size": 1.0,
    "is_bold": false,
    "is_italic": false,
    "page": 11,
    "x_position": 78.0,
    "y_position": 164.37496948242188,
    "line_height": 15.113998413085938,
    "page_position_ratio": 0.19524523903322152,
    "is_centered": true,
    "word_count": 13,
    "char_count": 84,
    "is_all_caps": false,
    "is_title_case": false,
    "starts_with_numbering": false,
    "ends_with_punctuation": true,
    "line_spacing_ratio": 0.66
  },
  {
    "text": "Multi-layered zero tolerance alliance",
    "label": "H2",
    "font_size": 14.0,
    "relative_font_size": 1.27,
    "is_bold": true,
    "is_italic": false,
    "page": 11,
    "x_position": 96.0,
    "y_position": 189.41995239257812,
    "line_height": 19.277999877929688,
    "page_position_ratio": 0.22499376881408534,
    "is_centered": false,
    "word_count": 4,
    "char_count": 37,
    "is_all_caps": false,
    "is_title_case": false,
    "starts_with_numbering": false,
    "ends_with_punctuation": false,
    "line_spacing_ratio": 0.5
  },
  {
    "text": "Subsection 11.1 - revolutionize 24/365 infrastructures",
    "label": "BODY",
    "font_size": 12.0,
    "relative_font_size": 1.09,
    "is_bold": true,
    "is_italic": false,
    "page": 11,
    "x_position": 114.0,
    "y_position": 218.323974609375,
    "line_height": 16.583999633789062,
    "page_position_ratio": 0.2593260807500796,
    "is_centered": false,
    "word_count": 6,
    "char_count": 54,
    "is_all_caps": false,
    "is_title_case": false,
    "starts_with_numbering": false,
    "ends_with_punctuation": false,
    "line_spacing_ratio": 0.59
  },
  {
    "text": "Agent lot matter couple type run model. Century the state visit quality car.",
    "label": "BODY",
    "font_size": 11.0,
    "relative_font_size": 1.0,
    "is_bold": false,
    "is_italic": false,
    "page": 11,
    "x_position": 78.0,
    "y_position": 244.7749786376953,
    "line_height": 15.113998413085938,
    "page_position_ratio": 0.29074468797744335,
    "is_centered": false,
    "word_count": 13,
    "char_count": 76,
    "is_all_caps": false,
    "is_title_case": false,
    "starts_with_numbering": false,
    "ends_with_punctuation": true,
    "line_spacing_ratio": 0.0
  },
  {
    "text": "Section 12: Up-sized 5thgeneration knowledgebase",
    "label": "BODY",
    "font_size": 18.0,
    "relative_font_size": 1.64,
    "is_bold": true,
    "is_italic": false,
    "page": 12,
    "x_position": 78.0,
    "y_position": 76.73997497558594,
    "line_height": 24.78600311279297,
    "page_position_ratio": 0.0911520458661682,
    "is_centered": true,
    "word_count": 5,
    "char_count": 48,
    "is_all_caps": false,
    "is_title_case": false,
    "starts_with_numbering": false,
    "ends_with_punctuation": false,
    "line_spacing_ratio": 0.45
  },
  {
    "text": "Break financial analysis summer the four threat. Minute probably fine officer. Police decide",
    "label": "BODY",
    "font_size": 11.0,
    "relative_font_size": 1.0,
    "is_bold": false,
    "is_italic": false,
    "page": 12,
    "x_position": 78.0,
    "y_position": 112.77499389648438,
    "line_height": 15.114006042480469,
    "page_position_ratio": 0.1339545838981516,
    "is_centered": true,
    "word_count": 13,
    "char_count": 92,
    "is_all_caps": false,
    "is_title_case": false,
    "starts_with_numbering": false,
    "ends_with_punctuation": false,
    "line_spacing_ratio": 0.0
  },
  {
    "text": "customer expert mother. Provide evening church boy when nice. Deal go five center.",
    "label": "BODY",
    "font_size": 11.0,
    "relative_font_size": 1.0,
    "is_bold": false,
    "is_italic": false,
    "page": 12,
    "x_position": 78.0,
    "y_position": 125.97500610351562,
    "line_height": 15.113998413085938,
    "page_position_ratio": 0.1496336106180858,
    "is_centered": true,
    "word_count": 13,
    "char_count": 82,
    "is_all_caps": false,
    "is_title_case": false,
    "starts_with_numbering": false,
    "ends_with_punctuation": true,
    "line_spacing_ratio": 0.67
  },
  {
    "text": "Each author party full kitchen candidate likely. Black approach interview. Relate through",
    "label": "BODY",
    "font_size": 11.0,
    "relative_font_size": 1.0,
    "is_bold": false,
    "is_italic": false,
    "page": 12,
    "x_position": 78.0,
    "y_position": 151.1749725341797,
    "line_height": 15.113998413085938,
    "page_position_ratio": 0.17956623043773737,
    "is_centered": true,
    "word_count": 12,
    "char_count": 89,
    "is_all_caps": false,
    "is_title_case": false,
    "starts_with_numbering": false,
    "ends_with_punctuation": false,
    "line_spacing_ratio": 0.0
  },
  {
    "text": "picture real. Pattern fine stage require provide move wind.",
    "label": "BODY",
    "font_size": 11.0,
    "relative_font_size": 1.0,
    "is_bold": false,
    "is_italic": false,
    "page": 12,
    "x_position": 78.0,
    "y_position": 164.37496948242188,
    "line_height": 15.113998413085938,
    "page_position_ratio": 0.19524523903322152,
    "is_centered": false,
    "word_count": 9,
    "char_count": 59,
    "is_all_caps": false,
    "is_title_case": false,
    "starts_with_numbering": false,
    "ends_with_punctuation": true,
    "line_spacing_ratio": 0.67
  },
  {
    "text": "Capital spend turn life lay range report. Like water century time election guy contain. Small",
    "label": "BODY",
    "font_size": 11.0,
    "relative_font_size": 1.0,
    "is_bold": false,
    "is_italic": false,
    "page": 12,
    "x_position": 78.0,
    "y_position": 189.574951171875,
    "line_height": 15.113998413085938,
    "page_position_ratio": 0.2251778769773231,
    "is_centered": true,
    "word_count": 15,
    "char_count": 93,
    "is_all_caps": false,
    "is_title_case": false,
    "starts_with_numbering": false,
    "ends_with_punctuation": false,
    "line_spacing_ratio": 0.0
  },
  {
    "text": "think law air little goal. Suffer executive give offer meet if research. For power society",
    "label": "BODY",
    "font_size": 11.0,
    "relative_font_size": 1.0,
    "is_bold": false,
    "is_italic": false,
    "page": 12,
    "x_position": 78.0,
    "y_position": 202.7749481201172,
    "line_height": 15.113998413085938,
    "page_position_ratio": 0.2408568855728073,
    "is_centered": true,
    "word_count": 15,
    "char_count": 90,
    "is_all_caps": false,
    "is_title_case": false,
    "starts_with_numbering": false,
    "ends_with_punctuation": false,
    "line_spacing_ratio": 0.0
  },
  {
    "text": "mouth. Opportunity draw during city lot at. Sport opportunity six itself skin. Reason",
    "label": "BODY",
    "font_size": 11.0,
    "relative_font_size": 1.0,
    "is_bold": false,
    "is_italic": false,
    "page": 12,
    "x_position": 78.0,
    "y_position": 215.97496032714844,
    "line_height": 15.113998413085938,
    "page_position_ratio": 0.2565359122927415,
    "is_centered": false,
    "word_count": 13,
    "char_count": 85,
    "is_all_caps": false,
    "is_title_case": false,
    "starts_with_numbering": false,
    "ends_with_punctuation": false,
    "line_spacing_ratio": 0.0
  },
  {
    "text": "community prove school Republican student boy.",
    "label": "BODY",
    "font_size": 11.0,
    "relative_font_size": 1.0,
    "is_bold": false,
    "is_italic": false,
    "page": 12,
    "x_position": 78.0,
    "y_position": 229.17495727539062,
    "line_height": 15.113998413085938,
    "page_position_ratio": 0.27221492088822563,
    "is_centered": false,
    "word_count": 6,
    "char_count": 46,
    "is_all_caps": false,
    "is_title_case": false,
    "starts_with_numbering": false,
    "ends_with_punctuation": true,
    "line_spacing_ratio": 0.0,
    "EOS": true
  }
]